<?xml version="1.0"?>
<?xml-stylesheet type='text/xsl' href='MessageLog.xsl'?>
<Log FirstSessionID="1" LastSessionID="26"><Message Date="7/5/2007" Time="2:22:47 PM" DateTime="2007-07-05T12:22:47.781Z" SessionID="1"><From><User FriendlyName="Stein"/></From><To><User FriendlyName="紫龙  在德国使用深圳、上海座机号码！ 龙腾科技"/></To><Text Style="font-family:MS Shell Dlg; color:#000000; ">这个怎么玩</Text></Message><Message Date="7/5/2007" Time="2:22:59 PM" DateTime="2007-07-05T12:22:59.015Z" SessionID="1"><From><User FriendlyName="紫龙  在德国使用深圳、上海座机号码！ 龙腾科技"/></From><To><User FriendlyName="Stein"/></To><Text Style="font-family:MS Shell Dlg; color:#000000; ">你发起邀请</Text></Message><Message Date="7/5/2007" Time="2:23:42 PM" DateTime="2007-07-05T12:23:42.390Z" SessionID="1"><From><User FriendlyName="Stein"/></From><To><User FriendlyName="紫龙  在德国使用深圳、上海座机号码！ 龙腾科技"/></To><Text Style="font-family:MS Shell Dlg; color:#000000; ">不知道在哪里哦</Text></Message><Message Date="7/5/2007" Time="2:32:15 PM" DateTime="2007-07-05T12:32:15.296Z" SessionID="1"><From><User FriendlyName="Stein"/></From><To><User FriendlyName="紫龙  在德国使用深圳、上海座机号码！ 龙腾科技"/></To><Text Style="font-family:MS Shell Dlg; color:#000000; "> Server Name:  
  Modell Nummer:  DSL Surf &amp; Phone 
  MAC-Adresse: 00:13:49:Df:ef:02 
  Firmwareversion:  V3.40(AOF.1)D0 | 4/23/2007 
  DSL-Firmwareversion:  TI AR7 07.03.00.67 
  WAN Internetverbindung    
      - IP-Adresse:  217.187.230.15 
      - Aktuelle Verbindung: 3:35:43 
      - Diensttyp: Surf-Flatrate 
  WAN VoIP-Verbindung    
      - IP-Adresse:  217.187.228.129 
  LAN-Informationen </Text></Message><Message Date="7/5/2007" Time="2:34:09 PM" DateTime="2007-07-05T12:34:09.234Z" SessionID="1"><From><User FriendlyName="Stein"/></From><To><User FriendlyName="紫龙  在德国使用深圳、上海座机号码！ 龙腾科技"/></To><Text Style="font-family:MS Shell Dlg; color:#000000; ">Firmware Version Ihres Geräts V3.40(AOF.1)D0 | 4/23/2007</Text></Message><Message Date="7/5/2007" Time="2:38:43 PM" DateTime="2007-07-05T12:38:43.515Z" SessionID="1"><From><User FriendlyName="紫龙  在德国使用深圳、上海座机号码！ 龙腾科技"/></From><To><User FriendlyName="Stein"/></To><Text Style="font-family:MS Shell Dlg; color:#000000; ">０２２１９４６５８０１２</Text></Message><Message Date="7/5/2007" Time="2:56:14 PM" DateTime="2007-07-05T12:56:14.937Z" SessionID="1"><From><User FriendlyName="紫龙  在德国使用深圳、上海座机号码！ 龙腾科技"/></From><To><User FriendlyName="Stein"/></To><Text Style="font-family:MS Shell Dlg; color:#000000; ">http://shop2.o2online.de/nw/produkte/dslinternet/dsl/tarife/uebersicht/pageframe.html?articleId=4530%20000241%2000&amp;salesChannel=SHOP&amp;duration=12&amp;tariffCode=O-DSL-H-S&amp;tariffCode_1=O-DSL-H-S&amp;tariffCode_2=O-DSL-H-M&amp;tariffCode_3=O-DSL-H-L</Text></Message><Message Date="7/5/2007" Time="3:21:42 PM" DateTime="2007-07-05T13:21:42.390Z" SessionID="1"><From><User FriendlyName="紫龙  在德国使用深圳、上海座机号码！ 龙腾科技"/></From><To><User FriendlyName="Stein"/></To><Text Style="font-family:MS Shell Dlg; color:#000000; ">http://cgi.ebay.de/o2-Surf-Home-II-UMTS-WLAN-Router-kein-Vertrag_W0QQitemZ330142470912QQihZ014QQcategoryZ132101QQcmdZViewItem</Text></Message><Message Date="7/5/2007" Time="3:21:45 PM" DateTime="2007-07-05T13:21:45.234Z" SessionID="1"><From><User FriendlyName="紫龙  在德国使用深圳、上海座机号码！ 龙腾科技"/></From><To><User FriendlyName="Stein"/></To><Text Style="font-family:MS Shell Dlg; color:#000000; ">http://www.o2online.de/nw/assets/blobs/dsl/o2-dsl-surf-phone-router.pdf</Text></Message><Message Date="8/3/2007" Time="6:29:00 PM" DateTime="2007-08-03T16:29:00.000Z" SessionID="2"><From><User FriendlyName="Stein"/></From><To><User FriendlyName="紫龙  在德国使用深圳、上海座机号码！ 龙腾科技"/></To><Text Style="font-family:MS Shell Dlg; color:#000000; ">你真辛苦，还没下班</Text></Message><Message Date="8/3/2007" Time="6:29:08 PM" DateTime="2007-08-03T16:29:08.437Z" SessionID="2"><From><User FriendlyName="紫龙  在德国使用深圳、上海座机号码！ 龙腾科技"/></From><To><User FriendlyName="Stein"/></To><Text Style="font-family:MS Shell Dlg; color:#000000; ">马上</Text></Message><Message Date="8/3/2007" Time="6:29:24 PM" DateTime="2007-08-03T16:29:24.703Z" SessionID="3"><From><User FriendlyName="Stein"/></From><To><User FriendlyName="紫龙  在德国使用深圳、上海座机号码！ 龙腾科技"/></To><Text Style="font-family:MS Shell Dlg; color:#000000; ">呵呵，，周末愉快！</Text></Message><Message Date="8/3/2007" Time="6:31:22 PM" DateTime="2007-08-03T16:31:22.781Z" SessionID="3"><From><User FriendlyName="紫龙  在德国使用深圳、上海座机号码！ 龙腾科技"/></From><To><User FriendlyName="Stein"/></To><Text Style="font-family:MS Shell Dlg; color:#000000; ">:)</Text></Message><Message Date="8/6/2007" Time="10:40:09 AM" DateTime="2007-08-06T08:40:09.064Z" SessionID="4"><From><User FriendlyName="Stein"/></From><To><User FriendlyName="紫龙  在德国使用深圳、上海座机号码！ 龙腾科技"/></To><Text Style="font-family:MS Shell Dlg; color:#000000; ">兄弟，我现在真的有些着急了。所有人都在抱怨我的电话。</Text></Message><Message Date="8/6/2007" Time="10:41:12 AM" DateTime="2007-08-06T08:41:12.142Z" SessionID="4"><From><User FriendlyName="Stein"/></From><To><User FriendlyName="紫龙  在德国使用深圳、上海座机号码！ 龙腾科技"/></To><Text Style="font-family:MS Shell Dlg; color:#000000; ">知道也给你添麻烦了，但我不知道找谁帮</Text></Message><Message Date="8/6/2007" Time="10:42:15 AM" DateTime="2007-08-06T08:42:15.251Z" SessionID="4"><From><User FriendlyName="紫龙  在德国使用深圳、上海座机号码！ 龙腾科技"/></From><To><User FriendlyName="Stein"/></To><Text Style="font-family:MS Shell Dlg; color:#000000; ">我给o2的service打了电话，那边的technik根本不懂。留了我的电话，会再打回来。</Text></Message><Message Date="8/6/2007" Time="10:43:28 AM" DateTime="2007-08-06T08:43:28.564Z" SessionID="4"><From><User FriendlyName="Stein"/></From><To><User FriendlyName="紫龙  在德国使用深圳、上海座机号码！ 龙腾科技"/></To><Text Style="font-family:MS Shell Dlg; color:#000000; ">咳，不好意思，难为你了</Text></Message><Message Date="8/6/2007" Time="10:43:45 AM" DateTime="2007-08-06T08:43:45.782Z" SessionID="4"><From><User FriendlyName="紫龙  在德国使用深圳、上海座机号码！ 龙腾科技"/></From><To><User FriendlyName="Stein"/></To><Text Style="font-family:MS Shell Dlg; color:#000000; ">测试设备后天会快递过来，多条路</Text></Message><Message Date="8/6/2007" Time="10:45:12 AM" DateTime="2007-08-06T08:45:12.564Z" SessionID="4"><From><User FriendlyName="Stein"/></From><To><User FriendlyName="紫龙  在德国使用深圳、上海座机号码！ 龙腾科技"/></To><Text Style="font-family:MS Shell Dlg; color:#000000; ">希望吧。。我都想砸了o2路由了</Text></Message><Message Date="8/6/2007" Time="10:45:54 AM" DateTime="2007-08-06T08:45:54.439Z" SessionID="4"><From><User FriendlyName="Stein"/></From><To><User FriendlyName="紫龙  在德国使用深圳、上海座机号码！ 龙腾科技"/></To><Text Style="font-family:MS Shell Dlg; color:#000000; ">不抱怨了，你工作吧</Text></Message><Message Date="8/6/2007" Time="10:46:48 AM" DateTime="2007-08-06T08:46:48.814Z" SessionID="4"><From><User FriendlyName="紫龙  在德国使用深圳、上海座机号码！ 龙腾科技"/></From><To><User FriendlyName="Stein"/></To><Text Style="font-family:MS Shell Dlg; color:#000000; ">理解，理解。我也加油</Text></Message><Message Date="8/6/2007" Time="10:47:22 AM" DateTime="2007-08-06T08:47:22.985Z" SessionID="4"><From><User FriendlyName="Stein"/></From><To><User FriendlyName="紫龙  在德国使用深圳、上海座机号码！ 龙腾科技"/></To><Text Style="font-family:MS Shell Dlg; color:#000000; ">发发牢骚，别见怪</Text></Message><Message Date="8/6/2007" Time="10:47:32 AM" DateTime="2007-08-06T08:47:32.985Z" SessionID="4"><From><User FriendlyName="紫龙  在德国使用深圳、上海座机号码！ 龙腾科技"/></From><To><User FriendlyName="Stein"/></To><Text Style="font-family:MS Shell Dlg; color:#000000; ">理解的</Text></Message><Message Date="8/6/2007" Time="10:47:42 AM" DateTime="2007-08-06T08:47:42.157Z" SessionID="4"><From><User FriendlyName="Stein"/></From><To><User FriendlyName="紫龙  在德国使用深圳、上海座机号码！ 龙腾科技"/></To><Text Style="font-family:MS Shell Dlg; color:#000000; ">谢谢</Text></Message><Message Date="8/6/2007" Time="10:48:03 AM" DateTime="2007-08-06T08:48:03.610Z" SessionID="4"><From><User FriendlyName="紫龙  在德国使用深圳、上海座机号码！ 龙腾科技"/></From><To><User FriendlyName="Stein"/></To><Text Style="font-family:MS Shell Dlg; color:#000000; ">:)</Text></Message><Message Date="8/15/2007" Time="11:50:07 AM" DateTime="2007-08-15T09:50:07.812Z" SessionID="5"><From><User FriendlyName="紫龙  在德国使用深圳、上海座机号码！ 龙腾科技"/></From><To><User FriendlyName="Stein"/></To><Text Style="font-family:MS Shell Dlg; color:#000000; ">明天有个专门的测试，针对你的故障的</Text></Message><Message Date="8/15/2007" Time="11:50:34 AM" DateTime="2007-08-15T09:50:34.250Z" SessionID="5"><From><User FriendlyName="Stein"/></From><To><User FriendlyName="紫龙  在德国使用深圳、上海座机号码！ 龙腾科技"/></To><Text Style="font-family:MS Shell Dlg; color:#000000; ">好的</Text></Message><Message Date="8/15/2007" Time="11:50:44 AM" DateTime="2007-08-15T09:50:44.906Z" SessionID="5"><From><User FriendlyName="Stein"/></From><To><User FriendlyName="紫龙  在德国使用深圳、上海座机号码！ 龙腾科技"/></To><Text Style="font-family:MS Shell Dlg; color:#000000; ">大概几点进行</Text></Message><Message Date="8/15/2007" Time="11:50:47 AM" DateTime="2007-08-15T09:50:47.609Z" SessionID="5"><From><User FriendlyName="紫龙  在德国使用深圳、上海座机号码！ 龙腾科技"/></From><To><User FriendlyName="Stein"/></To><Text Style="font-family:MS Shell Dlg; color:#000000; ">最近有什么新现象</Text></Message><Message Date="8/15/2007" Time="11:51:08 AM" DateTime="2007-08-15T09:51:08.890Z" SessionID="5"><From><User FriendlyName="紫龙  在德国使用深圳、上海座机号码！ 龙腾科技"/></From><To><User FriendlyName="Stein"/></To><Text Style="font-family:MS Shell Dlg; color:#000000; ">上午9点样子</Text></Message><Message Date="8/15/2007" Time="11:51:36 AM" DateTime="2007-08-15T09:51:36.687Z" SessionID="5"><From><User FriendlyName="Stein"/></From><To><User FriendlyName="紫龙  在德国使用深圳、上海座机号码！ 龙腾科技"/></To><Text Style="font-family:MS Shell Dlg; color:#000000; ">就是还是天天重启，其它都改善了</Text></Message><Message Date="8/15/2007" Time="11:51:37 AM" DateTime="2007-08-15T09:51:37.046Z" SessionID="5"><From><User FriendlyName="紫龙  在德国使用深圳、上海座机号码！ 龙腾科技"/></From><To><User FriendlyName="Stein"/></To><Text Style="font-family:MS Shell Dlg; color:#000000; ">要做好几个小时的数据截流</Text></Message><Message Date="8/15/2007" Time="11:52:12 AM" DateTime="2007-08-15T09:52:12.562Z" SessionID="5"><From><User FriendlyName="紫龙  在德国使用深圳、上海座机号码！ 龙腾科技"/></From><To><User FriendlyName="Stein"/></To><Text Style="font-family:MS Shell Dlg; color:#000000; ">重启动后，能用多长时间</Text></Message><Message Date="8/15/2007" Time="11:52:49 AM" DateTime="2007-08-15T09:52:49.359Z" SessionID="5"><From><User FriendlyName="Stein"/></From><To><User FriendlyName="紫龙  在德国使用深圳、上海座机号码！ 龙腾科技"/></To><Text Style="font-family:MS Shell Dlg; color:#000000; ">很难推算出来，大概也就10几个电话</Text></Message><Message Date="8/15/2007" Time="11:53:09 AM" DateTime="2007-08-15T09:53:09.734Z" SessionID="5"><From><User FriendlyName="紫龙  在德国使用深圳、上海座机号码！ 龙腾科技"/></From><To><User FriendlyName="Stein"/></To><Text Style="font-family:MS Shell Dlg; color:#000000; ">1个小时？</Text></Message><Message Date="8/15/2007" Time="11:53:41 AM" DateTime="2007-08-15T09:53:41.156Z" SessionID="5"><From><User FriendlyName="Stein"/></From><To><User FriendlyName="紫龙  在德国使用深圳、上海座机号码！ 龙腾科技"/></To><Text Style="font-family:MS Shell Dlg; color:#000000; ">没有，我哪里那么多电话进来，别人都不愿意打我电话了</Text></Message><Message Date="8/15/2007" Time="11:54:27 AM" DateTime="2007-08-15T09:54:27.250Z" SessionID="5"><From><User FriendlyName="紫龙  在德国使用深圳、上海座机号码！ 龙腾科技"/></From><To><User FriendlyName="Stein"/></To><Text Style="font-family:MS Shell Dlg; color:#000000; ">呵呵</Text></Message><Message Date="8/15/2007" Time="11:54:48 AM" DateTime="2007-08-15T09:54:48.328Z" SessionID="5"><From><User FriendlyName="Stein"/></From><To><User FriendlyName="紫龙  在德国使用深圳、上海座机号码！ 龙腾科技"/></To><Text Style="font-family:MS Shell Dlg; color:#000000; ">明天上午我有事不在家哦，怎么办呢</Text></Message><Message Date="8/15/2007" Time="11:55:15 AM" DateTime="2007-08-15T09:55:15.765Z" SessionID="5"><From><User FriendlyName="紫龙  在德国使用深圳、上海座机号码！ 龙腾科技"/></From><To><User FriendlyName="Stein"/></To><Text Style="font-family:MS Shell Dlg; color:#000000; ">o2的service也太滥了，我接电话的人不懂。写信过去不回</Text></Message><Message Date="8/15/2007" Time="11:55:21 AM" DateTime="2007-08-15T09:55:21.968Z" SessionID="5"><From><User FriendlyName="紫龙  在德国使用深圳、上海座机号码！ 龙腾科技"/></From><To><User FriendlyName="Stein"/></To><Text Style="font-family:MS Shell Dlg; color:#000000; ">没关系的</Text></Message><Message Date="8/15/2007" Time="11:56:01 AM" DateTime="2007-08-15T09:56:01.875Z" SessionID="5"><From><User FriendlyName="Stein"/></From><To><User FriendlyName="紫龙  在德国使用深圳、上海座机号码！ 龙腾科技"/></To><Text Style="font-family:MS Shell Dlg; color:#000000; ">我的这个问题是比较特殊的问题，没有研究的人肯定不知道的</Text></Message><Message Date="8/15/2007" Time="11:57:16 AM" DateTime="2007-08-15T09:57:16.656Z" SessionID="5"><From><User FriendlyName="Stein"/></From><To><User FriendlyName="紫龙  在德国使用深圳、上海座机号码！ 龙腾科技"/></To><Text Style="font-family:MS Shell Dlg; color:#000000; ">我需要做什么呢？你尽管吩咐</Text></Message><Message Date="8/15/2007" Time="11:58:17 AM" DateTime="2007-08-15T09:58:17.062Z" SessionID="5"><From><User FriendlyName="紫龙  在德国使用深圳、上海座机号码！ 龙腾科技"/></From><To><User FriendlyName="Stein"/></To><Text Style="font-family:MS Shell Dlg; color:#000000; ">你的电话也不会震岭，打过来你也会知道的，所以就无所谓了</Text></Message><Message Date="8/15/2007" Time="11:59:31 AM" DateTime="2007-08-15T09:59:31.640Z" SessionID="5"><From><User FriendlyName="Stein"/></From><To><User FriendlyName="紫龙  在德国使用深圳、上海座机号码！ 龙腾科技"/></To><Text Style="font-family:MS Shell Dlg; color:#000000; ">那我明天就不重启了，不然你就找不到毛病了</Text></Message><Message Date="8/15/2007" Time="12:00:59 PM" DateTime="2007-08-15T10:00:59.140Z" SessionID="5"><From><User FriendlyName="紫龙  在德国使用深圳、上海座机号码！ 龙腾科技"/></From><To><User FriendlyName="Stein"/></To><Text Style="font-family:MS Shell Dlg; color:#000000; ">恩，是的</Text></Message><Message Date="8/15/2007" Time="12:01:48 PM" DateTime="2007-08-15T10:01:48.843Z" SessionID="5"><From><User FriendlyName="Stein"/></From><To><User FriendlyName="紫龙  在德国使用深圳、上海座机号码！ 龙腾科技"/></To><Text Style="font-family:MS Shell Dlg; color:#000000; ">好的，我现在开始就不重启了</Text></Message><Message Date="8/15/2007" Time="12:02:05 PM" DateTime="2007-08-15T10:02:05.218Z" SessionID="5"><From><User FriendlyName="紫龙  在德国使用深圳、上海座机号码！ 龙腾科技"/></From><To><User FriendlyName="Stein"/></To><Text Style="font-family:MS Shell Dlg; color:#000000; ">今天无所谓的</Text></Message><Message Date="8/15/2007" Time="12:04:05 PM" DateTime="2007-08-15T10:04:05.531Z" SessionID="5"><From><User FriendlyName="Stein"/></From><To><User FriendlyName="紫龙  在德国使用深圳、上海座机号码！ 龙腾科技"/></To><Text Style="font-family:MS Shell Dlg; color:#000000; ">我会弄成不正常状态让你去试验</Text></Message><Message Date="8/15/2007" Time="12:04:52 PM" DateTime="2007-08-15T10:04:52.640Z" SessionID="5"><From><User FriendlyName="紫龙  在德国使用深圳、上海座机号码！ 龙腾科技"/></From><To><User FriendlyName="Stein"/></To><Text Style="font-family:MS Shell Dlg; color:#000000; ">因为会监控几个小时</Text></Message><Message Date="8/15/2007" Time="12:04:58 PM" DateTime="2007-08-15T10:04:58.562Z" SessionID="5"><From><User FriendlyName="紫龙  在德国使用深圳、上海座机号码！ 龙腾科技"/></From><To><User FriendlyName="Stein"/></To><Text Style="font-family:MS Shell Dlg; color:#000000; ">所以就无所谓了</Text></Message><Message Date="8/15/2007" Time="12:05:18 PM" DateTime="2007-08-15T10:05:18.750Z" SessionID="5"><From><User FriendlyName="Stein"/></From><To><User FriendlyName="紫龙  在德国使用深圳、上海座机号码！ 龙腾科技"/></To><Text Style="font-family:MS Shell Dlg; color:#000000; ">不过现在不会出现拿起电话挂机，这是一个大大的改善</Text></Message><Message Date="8/15/2007" Time="12:08:55 PM" DateTime="2007-08-15T10:08:55.781Z" SessionID="5"><From><User FriendlyName="Stein"/></From><To><User FriendlyName="紫龙  在德国使用深圳、上海座机号码！ 龙腾科技"/></To><Text Style="font-family:MS Shell Dlg; color:#000000; ">有个问题，电话你们打不进来了，那就一直打不进了哦，如果我不在家的话，没人重启盒子</Text></Message><Message Date="8/15/2007" Time="12:09:23 PM" DateTime="2007-08-15T10:09:23.109Z" SessionID="5"><From><User FriendlyName="紫龙  在德国使用深圳、上海座机号码！ 龙腾科技"/></From><To><User FriendlyName="Stein"/></To><Text Style="font-family:MS Shell Dlg; color:#000000; ">不用，正常状态的记录我们有</Text></Message><Message Date="8/15/2007" Time="12:09:35 PM" DateTime="2007-08-15T10:09:35.375Z" SessionID="5"><From><User FriendlyName="紫龙  在德国使用深圳、上海座机号码！ 龙腾科技"/></From><To><User FriendlyName="Stein"/></To><Text Style="font-family:MS Shell Dlg; color:#000000; ">主要记录，不正常状态</Text></Message><Message Date="8/15/2007" Time="12:10:51 PM" DateTime="2007-08-15T10:10:51.562Z" SessionID="5"><From><User FriendlyName="紫龙  在德国使用深圳、上海座机号码！ 龙腾科技"/></From><To><User FriendlyName="Stein"/></To><Text Style="font-family:MS Shell Dlg; color:#000000; ">然后分析</Text></Message><Message Date="8/15/2007" Time="12:11:49 PM" DateTime="2007-08-15T10:11:49.937Z" SessionID="5"><From><User FriendlyName="Stein"/></From><To><User FriendlyName="紫龙  在德国使用深圳、上海座机号码！ 龙腾科技"/></To><Text Style="font-family:MS Shell Dlg; color:#000000; ">那我今晚就把它弄成不正常的，明天你就直接测试了</Text></Message><Message Date="8/15/2007" Time="12:17:16 PM" DateTime="2007-08-15T10:17:16.703Z" SessionID="5"><From><User FriendlyName="紫龙  在德国使用深圳、上海座机号码！ 龙腾科技"/></From><To><User FriendlyName="Stein"/></To><Text Style="font-family:MS Shell Dlg; color:#000000; ">ok</Text></Message><Message Date="8/15/2007" Time="12:17:56 PM" DateTime="2007-08-15T10:17:56.937Z" SessionID="5"><From><User FriendlyName="Stein"/></From><To><User FriendlyName="紫龙  在德国使用深圳、上海座机号码！ 龙腾科技"/></To><Text Style="font-family:MS Shell Dlg; color:#000000; ">现在我几乎没人愿意给我电话，只有我自己弄了</Text></Message><Message Date="8/15/2007" Time="12:18:20 PM" DateTime="2007-08-15T10:18:20.640Z" SessionID="5"><From><User FriendlyName="Stein"/></From><To><User FriendlyName="紫龙  在德国使用深圳、上海座机号码！ 龙腾科技"/></To><Text Style="font-family:MS Shell Dlg; color:#000000; ">有空帮我看看我现在话费多少了</Text></Message><Message Date="8/15/2007" Time="12:21:39 PM" DateTime="2007-08-15T10:21:39.359Z" SessionID="5"><From><User FriendlyName="紫龙  在德国使用深圳、上海座机号码！ 龙腾科技"/></From><To><User FriendlyName="Stein"/></To><Text Style="font-family:MS Shell Dlg; color:#000000; ">pl</Text></Message><Message Date="8/15/2007" Time="12:21:45 PM" DateTime="2007-08-15T10:21:45.562Z" SessionID="5"><From><User FriendlyName="紫龙  在德国使用深圳、上海座机号码！ 龙腾科技"/></From><To><User FriendlyName="Stein"/></To><Text Style="font-family:MS Shell Dlg; color:#000000; ">ok</Text></Message><Message Date="8/16/2007" Time="10:58:09 AM" DateTime="2007-08-16T08:58:09.609Z" SessionID="6"><From><User FriendlyName="Stein"/></From><To><User FriendlyName="紫龙  在德国使用深圳、上海座机号码！ 龙腾科技"/></To><Text Style="font-family:MS Shell Dlg; color:#000000; ">我回来了</Text></Message><Message Date="8/16/2007" Time="10:58:22 AM" DateTime="2007-08-16T08:58:22.843Z" SessionID="6"><From><User FriendlyName="Stein"/></From><To><User FriendlyName="紫龙  在德国使用深圳、上海座机号码！ 龙腾科技"/></To><Text Style="font-family:MS Shell Dlg; color:#000000; ">你在测试吗</Text></Message><Message Date="8/16/2007" Time="11:09:56 AM" DateTime="2007-08-16T09:09:56.171Z" SessionID="6"><From><User FriendlyName="紫龙  在德国使用深圳、上海座机号码！ 龙腾科技"/></From><To><User FriendlyName="Stein"/></To><Text Style="font-family:MS Shell Dlg; color:#000000; ">我不在</Text></Message><Message Date="8/16/2007" Time="11:10:01 AM" DateTime="2007-08-16T09:10:01.468Z" SessionID="6"><From><User FriendlyName="紫龙  在德国使用深圳、上海座机号码！ 龙腾科技"/></From><To><User FriendlyName="Stein"/></To><Text Style="font-family:MS Shell Dlg; color:#000000; ">国内在做</Text></Message><Message Date="8/16/2007" Time="11:10:25 AM" DateTime="2007-08-16T09:10:25.953Z" SessionID="6"><From><User FriendlyName="Stein"/></From><To><User FriendlyName="紫龙  在德国使用深圳、上海座机号码！ 龙腾科技"/></To><Text Style="font-family:MS Shell Dlg; color:#000000; ">哦，需要我做什么配合吗</Text></Message><Message Date="8/16/2007" Time="11:10:44 AM" DateTime="2007-08-16T09:10:44.468Z" SessionID="6"><From><User FriendlyName="紫龙  在德国使用深圳、上海座机号码！ 龙腾科技"/></From><To><User FriendlyName="Stein"/></To><Text Style="font-family:MS Shell Dlg; color:#000000; ">不需要</Text></Message><Message Date="8/16/2007" Time="11:13:28 AM" DateTime="2007-08-16T09:13:28.500Z" SessionID="6"><From><User FriendlyName="Stein"/></From><To><User FriendlyName="紫龙  在德国使用深圳、上海座机号码！ 龙腾科技"/></To><Text Style="font-family:MS Shell Dlg; color:#000000; ">好的，结束了告诉我一声，我必须重启盒子的</Text></Message><Message Date="8/16/2007" Time="11:13:38 AM" DateTime="2007-08-16T09:13:38.421Z" SessionID="6"><From><User FriendlyName="紫龙  在德国使用深圳、上海座机号码！ 龙腾科技"/></From><To><User FriendlyName="Stein"/></To><Text Style="font-family:MS Shell Dlg; color:#000000; ">好的</Text></Message><Message Date="8/16/2007" Time="11:13:47 AM" DateTime="2007-08-16T09:13:47.203Z" SessionID="6"><From><User FriendlyName="紫龙  在德国使用深圳、上海座机号码！ 龙腾科技"/></From><To><User FriendlyName="Stein"/></To><Text Style="font-family:MS Shell Dlg; color:#000000; ">那边一直在纪录数据</Text></Message><Message Date="8/16/2007" Time="11:14:53 AM" DateTime="2007-08-16T09:14:53.828Z" SessionID="6"><From><User FriendlyName="紫龙  在德国使用深圳、上海座机号码！ 龙腾科技"/></From><To><User FriendlyName="Stein"/></To><Text Style="font-family:MS Shell Dlg; color:#000000; ">你5分钟后可以重新启动</Text></Message><Message Date="8/16/2007" Time="11:16:02 AM" DateTime="2007-08-16T09:16:02.843Z" SessionID="6"><From><User FriendlyName="Stein"/></From><To><User FriendlyName="紫龙  在德国使用深圳、上海座机号码！ 龙腾科技"/></To><Text Style="font-family:MS Shell Dlg; color:#000000; ">我的感觉是， 如果重启后，不拨出电话大概可以接大约5个电话，如果当中我有拨出电话，那么接不到电话的概率会增加</Text></Message><Message Date="8/16/2007" Time="11:21:41 AM" DateTime="2007-08-16T09:21:41.531Z" SessionID="6"><From><User FriendlyName="Stein"/></From><To><User FriendlyName="紫龙  在德国使用深圳、上海座机号码！ 龙腾科技"/></To><Text Style="font-family:MS Shell Dlg; color:#000000; ">我现在重启盒子</Text></Message><Message Date="8/16/2007" Time="11:26:12 AM" DateTime="2007-08-16T09:26:12.437Z" SessionID="6"><From><User FriendlyName="紫龙  在德国使用深圳、上海座机号码！ 龙腾科技"/></From><To><User FriendlyName="Stein"/></To><Text Style="font-family:MS Shell Dlg; color:#000000; ">好</Text></Message><Message Date="8/16/2007" Time="11:43:32 AM" DateTime="2007-08-16T09:43:32.500Z" SessionID="6"><From><User FriendlyName="Stein"/></From><To><User FriendlyName="紫龙  在德国使用深圳、上海座机号码！ 龙腾科技"/></To><Text Style="font-family:MS Shell Dlg; color:#000000; ">测试结束了？</Text></Message><Message Date="8/16/2007" Time="11:46:41 AM" DateTime="2007-08-16T09:46:41.703Z" SessionID="6"><From><User FriendlyName="紫龙  在德国使用深圳、上海座机号码！ 龙腾科技"/></From><To><User FriendlyName="Stein"/></To><Text Style="font-family:MS Shell Dlg; color:#000000; ">对</Text></Message><Message Date="8/16/2007" Time="11:47:38 AM" DateTime="2007-08-16T09:47:38.515Z" SessionID="6"><From><User FriendlyName="Stein"/></From><To><User FriendlyName="紫龙  在德国使用深圳、上海座机号码！ 龙腾科技"/></To><Text Style="font-family:MS Shell Dlg; color:#000000; ">哦，有消息告诉我</Text></Message><Message Date="8/16/2007" Time="5:32:31 PM" DateTime="2007-08-16T15:32:31.875Z" SessionID="7"><From><User FriendlyName="Stein"/></From><To><User FriendlyName="紫龙  在德国使用深圳、上海座机号码！ 龙腾科技"/></To><Text Style="font-family:MS Shell Dlg; color:#000000; ">最近好像你一直都很忙</Text></Message><Message Date="8/16/2007" Time="5:32:59 PM" DateTime="2007-08-16T15:32:59.671Z" SessionID="7"><From><User FriendlyName="紫龙  在德国使用深圳、上海座机号码！ 龙腾科技"/></From><To><User FriendlyName="Stein"/></To><Text Style="font-family:MS Shell Dlg; color:#000000; ">是地</Text></Message><Message Date="8/16/2007" Time="5:33:33 PM" DateTime="2007-08-16T15:33:33.375Z" SessionID="7"><From><User FriendlyName="Stein"/></From><To><User FriendlyName="紫龙  在德国使用深圳、上海座机号码！ 龙腾科技"/></To><Text Style="font-family:MS Shell Dlg; color:#000000; ">有钱挣就好</Text></Message><Message Date="8/16/2007" Time="5:33:50 PM" DateTime="2007-08-16T15:33:50.109Z" SessionID="7"><From><User FriendlyName="紫龙  在德国使用深圳、上海座机号码！ 龙腾科技"/></From><To><User FriendlyName="Stein"/></To><Text Style="font-family:MS Shell Dlg; color:#000000; ">累</Text></Message><Message Date="8/16/2007" Time="5:34:56 PM" DateTime="2007-08-16T15:34:56.921Z" SessionID="7"><From><User FriendlyName="Stein"/></From><To><User FriendlyName="紫龙  在德国使用深圳、上海座机号码！ 龙腾科技"/></To><Text Style="font-family:MS Shell Dlg; color:#000000; ">可以想象，但心不要太累</Text></Message><Message Date="8/16/2007" Time="5:35:36 PM" DateTime="2007-08-16T15:35:36.906Z" SessionID="7"><From><User FriendlyName="紫龙  在德国使用深圳、上海座机号码！ 龙腾科技"/></From><To><User FriendlyName="Stein"/></To><Text Style="font-family:MS Shell Dlg; color:#000000; ">人老心不老</Text></Message><Message Date="8/16/2007" Time="5:35:41 PM" DateTime="2007-08-16T15:35:41.718Z" SessionID="7"><From><User FriendlyName="紫龙  在德国使用深圳、上海座机号码！ 龙腾科技"/></From><To><User FriendlyName="Stein"/></To><Text Style="font-family:MS Shell Dlg; color:#000000; ">:D</Text></Message><Message Date="8/16/2007" Time="5:36:21 PM" DateTime="2007-08-16T15:36:21.796Z" SessionID="7"><From><User FriendlyName="Stein"/></From><To><User FriendlyName="紫龙  在德国使用深圳、上海座机号码！ 龙腾科技"/></To><Text Style="font-family:MS Shell Dlg; color:#000000; ">我听得出，你的心态很好</Text></Message><Message Date="8/16/2007" Time="5:37:07 PM" DateTime="2007-08-16T15:37:07.500Z" SessionID="7"><From><User FriendlyName="紫龙  在德国使用深圳、上海座机号码！ 龙腾科技"/></From><To><User FriendlyName="Stein"/></To><Text Style="font-family:MS Shell Dlg; color:#000000; ">:)</Text></Message><Message Date="8/16/2007" Time="5:37:20 PM" DateTime="2007-08-16T15:37:20.656Z" SessionID="7"><From><User FriendlyName="紫龙  在德国使用深圳、上海座机号码！ 龙腾科技"/></From><To><User FriendlyName="Stein"/></To><Text Style="font-family:MS Shell Dlg; color:#000000; ">国内的分析结果还没有出来</Text></Message><Message Date="8/16/2007" Time="5:37:51 PM" DateTime="2007-08-16T15:37:51.578Z" SessionID="7"><From><User FriendlyName="紫龙  在德国使用深圳、上海座机号码！ 龙腾科技"/></From><To><User FriendlyName="Stein"/></To><Text Style="font-family:MS Shell Dlg; color:#000000; ">我再等着他们的解决办法</Text></Message><Message Date="8/16/2007" Time="5:38:28 PM" DateTime="2007-08-16T15:38:28.859Z" SessionID="7"><From><User FriendlyName="Stein"/></From><To><User FriendlyName="紫龙  在德国使用深圳、上海座机号码！ 龙腾科技"/></To><Text Style="font-family:MS Shell Dlg; color:#000000; ">哪里那么快啊，</Text></Message><Message Date="8/16/2007" Time="5:39:35 PM" DateTime="2007-08-16T15:39:35.328Z" SessionID="7"><From><User FriendlyName="Stein"/></From><To><User FriendlyName="紫龙  在德国使用深圳、上海座机号码！ 龙腾科技"/></To><Text Style="font-family:MS Shell Dlg; color:#000000; ">别和我说你的labor现在还在工作</Text></Message><Message Date="8/16/2007" Time="5:40:11 PM" DateTime="2007-08-16T15:40:11.921Z" SessionID="7"><From><User FriendlyName="紫龙  在德国使用深圳、上海座机号码！ 龙腾科技"/></From><To><User FriendlyName="Stein"/></To><Text Style="font-family:MS Shell Dlg; color:#000000; ">他们加了会班，不过现在都下线了</Text></Message><Message Date="8/16/2007" Time="5:40:54 PM" DateTime="2007-08-16T15:40:54.015Z" SessionID="7"><From><User FriendlyName="Stein"/></From><To><User FriendlyName="紫龙  在德国使用深圳、上海座机号码！ 龙腾科技"/></To><Text Style="font-family:MS Shell Dlg; color:#000000; ">就是，你不能做外国资本家的。。</Text></Message><Message Date="8/16/2007" Time="5:44:31 PM" DateTime="2007-08-16T15:44:31.046Z" SessionID="7"><From><User FriendlyName="紫龙  在德国使用深圳、上海座机号码！ 龙腾科技"/></From><To><User FriendlyName="Stein"/></To><Text Style="font-family:MS Shell Dlg; color:#000000; ">:)</Text></Message><Message Date="8/16/2007" Time="5:45:27 PM" DateTime="2007-08-16T15:45:27.093Z" SessionID="7"><From><User FriendlyName="紫龙  在德国使用深圳、上海座机号码！ 龙腾科技"/></From><To><User FriendlyName="Stein"/></To><Text Style="font-family:MS Shell Dlg; color:#000000; ">我和这帮技术员，都是兄弟相称得。有几个都比我略大点</Text></Message><Message Date="8/16/2007" Time="5:45:48 PM" DateTime="2007-08-16T15:45:48.203Z" SessionID="7"><From><User FriendlyName="紫龙  在德国使用深圳、上海座机号码！ 龙腾科技"/></From><To><User FriendlyName="Stein"/></To><Text Style="font-family:MS Shell Dlg; color:#000000; ">我还得交声大佬</Text></Message><Message Date="8/16/2007" Time="5:45:52 PM" DateTime="2007-08-16T15:45:52.281Z" SessionID="7"><From><User FriendlyName="紫龙  在德国使用深圳、上海座机号码！ 龙腾科技"/></From><To><User FriendlyName="Stein"/></To><Text Style="font-family:MS Shell Dlg; color:#000000; ">:)</Text></Message><Message Date="8/16/2007" Time="5:46:52 PM" DateTime="2007-08-16T15:46:52.093Z" SessionID="7"><From><User FriendlyName="Stein"/></From><To><User FriendlyName="紫龙  在德国使用深圳、上海座机号码！ 龙腾科技"/></To><Text Style="font-family:MS Shell Dlg; color:#000000; ">不过你得付兄弟工资的哦，别拖欠了，，，你压力好大</Text></Message><Message Date="8/16/2007" Time="5:48:15 PM" DateTime="2007-08-16T15:48:15.875Z" SessionID="7"><From><User FriendlyName="Stein"/></From><To><User FriendlyName="紫龙  在德国使用深圳、上海座机号码！ 龙腾科技"/></To><Text Style="font-family:MS Shell Dlg; color:#000000; ">不过有一帮这样的兄弟可以合作，真的是很开心的</Text></Message><Message Date="8/16/2007" Time="5:52:51 PM" DateTime="2007-08-16T15:52:51.875Z" SessionID="7"><From><User FriendlyName="紫龙  在德国使用深圳、上海座机号码！ 龙腾科技"/></From><To><User FriendlyName="Stein"/></To><Text Style="font-family:MS Shell Dlg; color:#000000; ">恩。理解万岁</Text></Message><Message Date="8/16/2007" Time="6:07:15 PM" DateTime="2007-08-16T16:07:15.515Z" SessionID="7"><From><User FriendlyName="Stein"/></From><To><User FriendlyName="紫龙  在德国使用深圳、上海座机号码！ 龙腾科技"/></To><Text Style="font-family:MS Shell Dlg; color:#000000; ">龙弟，</Text></Message><Message Date="8/16/2007" Time="6:07:23 PM" DateTime="2007-08-16T16:07:23.703Z" SessionID="7"><From><User FriendlyName="紫龙  在德国使用深圳、上海座机号码！ 龙腾科技"/></From><To><User FriendlyName="Stein"/></To><Text Style="font-family:MS Shell Dlg; color:#000000; ">:D</Text></Message><Message Date="8/16/2007" Time="6:07:47 PM" DateTime="2007-08-16T16:07:47.281Z" SessionID="7"><From><User FriendlyName="Stein"/></From><To><User FriendlyName="紫龙  在德国使用深圳、上海座机号码！ 龙腾科技"/></To><Text Style="font-family:MS Shell Dlg; color:#000000; ">我朋友打我电话，提示为关机</Text></Message><Message Date="8/16/2007" Time="6:07:59 PM" DateTime="2007-08-16T16:07:59.781Z" SessionID="7"><From><User FriendlyName="Stein"/></From><To><User FriendlyName="紫龙  在德国使用深圳、上海座机号码！ 龙腾科技"/></To><Text Style="font-family:MS Shell Dlg; color:#000000; ">现在打的</Text></Message><Message Date="8/16/2007" Time="6:08:16 PM" DateTime="2007-08-16T16:08:16.312Z" SessionID="7"><From><User FriendlyName="Stein"/></From><To><User FriendlyName="紫龙  在德国使用深圳、上海座机号码！ 龙腾科技"/></To><Text Style="font-family:MS Shell Dlg; color:#000000; ">我不是手机，怎么会提示关机呢</Text></Message><Message Date="8/16/2007" Time="6:09:55 PM" DateTime="2007-08-16T16:09:55.515Z" SessionID="7"><From><User FriendlyName="紫龙  在德国使用深圳、上海座机号码！ 龙腾科技"/></From><To><User FriendlyName="Stein"/></To><Text Style="font-family:MS Shell Dlg; color:#000000; ">只要号码存在，但又不能接通，国内一般就会让系统处理成关机</Text></Message><Message Date="8/16/2007" Time="6:10:40 PM" DateTime="2007-08-16T16:10:40.593Z" SessionID="7"><From><User FriendlyName="Stein"/></From><To><User FriendlyName="紫龙  在德国使用深圳、上海座机号码！ 龙腾科技"/></To><Text Style="font-family:MS Shell Dlg; color:#000000; ">哦，，，知道了，不去管它了，重启就好了</Text></Message><Message Date="8/16/2007" Time="6:10:47 PM" DateTime="2007-08-16T16:10:47.546Z" SessionID="7"><From><User FriendlyName="紫龙  在德国使用深圳、上海座机号码！ 龙腾科技"/></From><To><User FriendlyName="Stein"/></To><Text Style="font-family:MS Shell Dlg; color:#000000; ">恩</Text></Message><Message Date="8/20/2007" Time="5:36:44 PM" DateTime="2007-08-20T15:36:44.250Z" SessionID="8"><From><User FriendlyName="Stein"/></From><To><User FriendlyName="紫龙  在德国使用深圳、上海座机号码！ 龙腾科技"/></To><Text Style="font-family:MS Shell Dlg; color:#000000; ">刚才打出去电话，对方听不到我声音</Text></Message><Message Date="8/20/2007" Time="5:37:33 PM" DateTime="2007-08-20T15:37:33.140Z" SessionID="8"><From><User FriendlyName="紫龙  在德国使用深圳、上海座机号码！ 龙腾科技"/></From><To><User FriendlyName="Stein"/></To><Text Style="font-family:MS Shell Dlg; color:#000000; ">哦</Text></Message><Message Date="8/20/2007" Time="5:39:14 PM" DateTime="2007-08-20T15:39:14.484Z" SessionID="8"><From><User FriendlyName="Stein"/></From><To><User FriendlyName="紫龙  在德国使用深圳、上海座机号码！ 龙腾科技"/></To><Text Style="font-family:MS Shell Dlg; color:#000000; ">而且现在，响铃一次就必须重启盒子</Text></Message><Message Date="8/20/2007" Time="5:39:41 PM" DateTime="2007-08-20T15:39:41.890Z" SessionID="8"><From><User FriendlyName="紫龙  在德国使用深圳、上海座机号码！ 龙腾科技"/></From><To><User FriendlyName="Stein"/></To><Text Style="font-family:MS Shell Dlg; color:#000000; ">你重新启动一下路由</Text></Message><Message Date="8/20/2007" Time="5:39:54 PM" DateTime="2007-08-20T15:39:54.109Z" SessionID="8"><From><User FriendlyName="紫龙  在德国使用深圳、上海座机号码！ 龙腾科技"/></From><To><User FriendlyName="Stein"/></To><Text Style="font-family:MS Shell Dlg; color:#000000; ">国内已经停止测试了</Text></Message><Message Date="8/20/2007" Time="5:40:11 PM" DateTime="2007-08-20T15:40:11.578Z" SessionID="8"><From><User FriendlyName="紫龙  在德国使用深圳、上海座机号码！ 龙腾科技"/></From><To><User FriendlyName="Stein"/></To><Text Style="font-family:MS Shell Dlg; color:#000000; ">我这里通话正常，刚试了</Text></Message><Message Date="8/20/2007" Time="5:40:14 PM" DateTime="2007-08-20T15:40:14.390Z" SessionID="8"><From><User FriendlyName="Stein"/></From><To><User FriendlyName="紫龙  在德国使用深圳、上海座机号码！ 龙腾科技"/></To><Text Style="font-family:MS Shell Dlg; color:#000000; ">哦，好的</Text></Message><Message Date="8/24/2007" Time="1:46:58 PM" DateTime="2007-08-24T11:46:58.578Z" SessionID="9"><From><User FriendlyName="Stein"/></From><To><User FriendlyName="紫龙  深圳、上海、广州座机号码，热销中！ 龙腾科技"/></To><Text Style="font-family:MS Shell Dlg; color:#000000; ">龙弟，啥时候开始呢</Text></Message><Message Date="8/24/2007" Time="1:47:16 PM" DateTime="2007-08-24T11:47:16.297Z" SessionID="9"><From><User FriendlyName="紫龙  深圳、上海、广州座机号码，热销中！ 龙腾科技"/></From><To><User FriendlyName="Stein"/></To><Text Style="font-family:MS Shell Dlg; color:#000000; ">对了，正要给你写信</Text></Message><Message Date="8/24/2007" Time="1:47:35 PM" DateTime="2007-08-24T11:47:35.188Z" SessionID="9"><From><User FriendlyName="Stein"/></From><To><User FriendlyName="紫龙  深圳、上海、广州座机号码，热销中！ 龙腾科技"/></To><Text Style="font-family:MS Shell Dlg; color:#000000; ">默契嘛，呵呵</Text></Message><Message Date="8/24/2007" Time="1:47:52 PM" DateTime="2007-08-24T11:47:52.438Z" SessionID="9"><From><User FriendlyName="紫龙  深圳、上海、广州座机号码，热销中！ 龙腾科技"/></From><To><User FriendlyName="Stein"/></To><Text Style="font-family:MS Shell Dlg; color:#000000; ">程序他们是发过来了，我刚才在我的机器上升级，结果升死机了</Text></Message><Message Date="8/24/2007" Time="1:48:30 PM" DateTime="2007-08-24T11:48:30.938Z" SessionID="9"><From><User FriendlyName="紫龙  深圳、上海、广州座机号码，热销中！ 龙腾科技"/></From><To><User FriendlyName="Stein"/></To><Text Style="font-family:MS Shell Dlg; color:#000000; ">今天估计不能和你测试了</Text></Message><Message Date="8/24/2007" Time="1:48:36 PM" DateTime="2007-08-24T11:48:36.813Z" SessionID="9"><From><User FriendlyName="Stein"/></From><To><User FriendlyName="紫龙  深圳、上海、广州座机号码，热销中！ 龙腾科技"/></To><Text Style="font-family:MS Shell Dlg; color:#000000; ">哦</Text></Message><Message Date="8/24/2007" Time="1:49:17 PM" DateTime="2007-08-24T11:49:17.188Z" SessionID="9"><From><User FriendlyName="Stein"/></From><To><User FriendlyName="紫龙  深圳、上海、广州座机号码，热销中！ 龙腾科技"/></To><Text Style="font-family:MS Shell Dlg; color:#000000; ">那就再说只有</Text></Message><Message Date="8/24/2007" Time="1:49:29 PM" DateTime="2007-08-24T11:49:29.860Z" SessionID="9"><From><User FriendlyName="紫龙  深圳、上海、广州座机号码，热销中！ 龙腾科技"/></From><To><User FriendlyName="Stein"/></To><Text Style="font-family:MS Shell Dlg; color:#000000; ">=</Text></Message><Message Date="8/24/2007" Time="1:50:45 PM" DateTime="2007-08-24T11:50:45.047Z" SessionID="9"><From><User FriendlyName="紫龙  深圳、上海、广州座机号码，热销中！ 龙腾科技"/></From><To><User FriendlyName="Stein"/></To><Text Style="font-family:MS Shell Dlg; color:#000000; ">修改程序的工程师还在加班。但不能确定今天能否出来</Text></Message><Message Date="8/24/2007" Time="1:51:22 PM" DateTime="2007-08-24T11:51:22.563Z" SessionID="9"><From><User FriendlyName="Stein"/></From><To><User FriendlyName="紫龙  深圳、上海、广州座机号码，热销中！ 龙腾科技"/></To><Text Style="font-family:MS Shell Dlg; color:#000000; ">没关系，我理解的</Text></Message><Message Date="8/24/2007" Time="1:52:17 PM" DateTime="2007-08-24T11:52:17.656Z" SessionID="9"><From><User FriendlyName="紫龙  深圳、上海、广州座机号码，热销中！ 龙腾科技"/></From><To><User FriendlyName="Stein"/></To><Text Style="font-family:MS Shell Dlg; color:#000000; ">只有再==。今天周五，不要意思要他们干太晚</Text></Message><Message Date="8/24/2007" Time="1:52:42 PM" DateTime="2007-08-24T11:52:42.563Z" SessionID="9"><From><User FriendlyName="Stein"/></From><To><User FriendlyName="紫龙  深圳、上海、广州座机号码，热销中！ 龙腾科技"/></To><Text Style="font-family:MS Shell Dlg; color:#000000; ">是的，不在乎这么几天的</Text></Message><Message Date="8/24/2007" Time="1:53:27 PM" DateTime="2007-08-24T11:53:27.344Z" SessionID="9"><From><User FriendlyName="紫龙  深圳、上海、广州座机号码，热销中！ 龙腾科技"/></From><To><User FriendlyName="Stein"/></To><Text Style="font-family:MS Shell Dlg; color:#000000; ">恩，谢谢理解</Text></Message><Message Date="8/24/2007" Time="1:53:59 PM" DateTime="2007-08-24T11:53:59.985Z" SessionID="9"><From><User FriendlyName="Stein"/></From><To><User FriendlyName="紫龙  深圳、上海、广州座机号码，热销中！ 龙腾科技"/></To><Text Style="font-family:MS Shell Dlg; color:#000000; ">不过报告一下我的新状态，每次重启盒子，只能接一次的电话</Text></Message><Message Date="8/24/2007" Time="1:54:49 PM" DateTime="2007-08-24T11:54:49.781Z" SessionID="9"><From><User FriendlyName="Stein"/></From><To><User FriendlyName="紫龙  深圳、上海、广州座机号码，热销中！ 龙腾科技"/></To><Text Style="font-family:MS Shell Dlg; color:#000000; ">希望这信息对你有用</Text></Message><Message Date="8/24/2007" Time="1:57:45 PM" DateTime="2007-08-24T11:57:45.578Z" SessionID="9"><From><User FriendlyName="紫龙  深圳、上海、广州座机号码，热销中！ 龙腾科技"/></From><To><User FriendlyName="Stein"/></To><Text Style="font-family:MS Shell Dlg; color:#000000; ">恩，这次改进应该能解决这个问题。你重启动路由器，应该能多接通几次吧？</Text></Message><Message Date="8/24/2007" Time="1:59:05 PM" DateTime="2007-08-24T11:59:05.719Z" SessionID="9"><From><User FriendlyName="Stein"/></From><To><User FriendlyName="紫龙  深圳、上海、广州座机号码，热销中！ 龙腾科技"/></To><Text Style="font-family:MS Shell Dlg; color:#000000; ">在测试前还好，能接蛮多的</Text></Message><Message Date="8/24/2007" Time="2:00:20 PM" DateTime="2007-08-24T12:00:20.625Z" SessionID="9"><From><User FriendlyName="Stein"/></From><To><User FriendlyName="紫龙  深圳、上海、广州座机号码，热销中！ 龙腾科技"/></To><Text Style="font-family:MS Shell Dlg; color:#000000; ">上次更新最明显的变化，就是不再听到铃声，拿起电话就挂机的现象</Text></Message><Message Date="8/24/2007" Time="2:00:21 PM" DateTime="2007-08-24T12:00:21.094Z" SessionID="9"><From><User FriendlyName="紫龙  深圳、上海、广州座机号码，热销中！ 龙腾科技"/></From><To><User FriendlyName="Stein"/></To><Text Style="font-family:MS Shell Dlg; color:#000000; ">这两天已经没有测了，一直在改进</Text></Message><Message Date="8/25/2007" Time="9:11:14 AM" DateTime="2007-08-25T07:11:14.906Z" SessionID="10"><From><User FriendlyName="Stein"/></From><To><User FriendlyName="紫龙  深圳、上海、广州座机号码，热销中！ 龙腾科技"/></To><Text Style="font-family:MS Shell Dlg; color:#000000; ">今天还加班？</Text></Message><Message Date="8/25/2007" Time="9:26:03 AM" DateTime="2007-08-25T07:26:03.781Z" SessionID="10"><From><User FriendlyName="紫龙  深圳、上海、广州座机号码，热销中！ 龙腾科技"/></From><To><User FriendlyName="Stein"/></To><Text Style="font-family:MS Shell Dlg; color:#000000; ">恩。有个约，先下啦</Text></Message><Message Date="8/29/2007" Time="10:09:36 PM" DateTime="2007-08-29T20:09:36.468Z" SessionID="11"><From><User FriendlyName="Stein"/></From><To><User FriendlyName="紫龙  深圳、上海、广州座机号码，热销中！ 龙腾科技"/></To><Text Style="font-family:Microsoft Sans Serif; font-weight:bold; color:#000000; ">龙弟</Text></Message><Message Date="8/29/2007" Time="10:09:59 PM" DateTime="2007-08-29T20:09:59.562Z" SessionID="11"><From><User FriendlyName="紫龙  深圳、上海、广州座机号码，热销中！ 龙腾科技"/></From><To><User FriendlyName="Stein"/></To><Text Style="font-family:MS Shell Dlg; color:#000000; ">hi</Text></Message><Message Date="8/29/2007" Time="10:10:20 PM" DateTime="2007-08-29T20:10:20.218Z" SessionID="11"><From><User FriendlyName="Stein"/></From><To><User FriendlyName="紫龙  深圳、上海、广州座机号码，热销中！ 龙腾科技"/></To><Text Style="font-family:Microsoft Sans Serif; font-weight:bold; color:#000000; ">你最近挺忙</Text></Message><Message Date="8/29/2007" Time="10:12:36 PM" DateTime="2007-08-29T20:12:36.078Z" SessionID="11"><From><User FriendlyName="紫龙  深圳、上海、广州座机号码，热销中！ 龙腾科技"/></From><To><User FriendlyName="Stein"/></To><Text Style="font-family:MS Shell Dlg; color:#000000; ">恩，是地</Text></Message><Message Date="8/29/2007" Time="10:13:03 PM" DateTime="2007-08-29T20:13:03.171Z" SessionID="11"><From><User FriendlyName="Stein"/></From><To><User FriendlyName="紫龙  深圳、上海、广州座机号码，热销中！ 龙腾科技"/></To><Text Style="font-family:Microsoft Sans Serif; font-weight:bold; color:#000000; ">不打扰了，你忙吧</Text></Message><Message Date="8/29/2007" Time="10:13:40 PM" DateTime="2007-08-29T20:13:40.734Z" SessionID="11"><From><User FriendlyName="紫龙  深圳、上海、广州座机号码，热销中！ 龙腾科技"/></From><To><User FriendlyName="Stein"/></To><Text Style="font-family:MS Shell Dlg; color:#000000; ">回聊</Text></Message><Message Date="9/1/2007" Time="8:54:48 PM" DateTime="2007-09-01T18:54:48.687Z" SessionID="12"><From><User FriendlyName="Stein"/></From><To><User FriendlyName="紫龙  深圳、上海、广州座机号码，热销中！ 龙腾科技"/></To><Text Style="font-family:Microsoft Sans Serif; font-weight:bold; color:#000000; ">hi</Text></Message><Message Date="9/1/2007" Time="8:54:49 PM" DateTime="2007-09-01T18:54:49.375Z" SessionID="12"><From><User FriendlyName="Stein"/></From><To><User FriendlyName="紫龙  深圳、上海、广州座机号码，热销中！ 龙腾科技"/></To><Text Style="font-family:Microsoft Sans Serif; font-weight:bold; color:#000000; ">还在忙呢</Text></Message><Message Date="9/1/2007" Time="8:55:10 PM" DateTime="2007-09-01T18:55:10.968Z" SessionID="12"><From><User FriendlyName="紫龙  深圳、上海、广州座机号码，热销中！ 龙腾科技"/></From><To><User FriendlyName="Stein"/></To><Text Style="font-family:MS Shell Dlg; color:#000000; ">是地</Text></Message><Message Date="9/1/2007" Time="8:56:25 PM" DateTime="2007-09-01T18:56:25.000Z" SessionID="12"><From><User FriendlyName="紫龙  深圳、上海、广州座机号码，热销中！ 龙腾科技"/></From><To><User FriendlyName="Stein"/></To><Text Style="font-family:MS Shell Dlg; color:#000000; ">升级下周能出来了</Text></Message><Message Date="9/1/2007" Time="8:56:48 PM" DateTime="2007-09-01T18:56:48.484Z" SessionID="12"><From><User FriendlyName="Stein"/></From><To><User FriendlyName="紫龙  深圳、上海、广州座机号码，热销中！ 龙腾科技"/></To><Text Style="font-family:Microsoft Sans Serif; font-weight:bold; color:#000000; ">没事，就是和你招呼一声的</Text></Message><Message Date="9/1/2007" Time="8:57:17 PM" DateTime="2007-09-01T18:57:17.359Z" SessionID="12"><From><User FriendlyName="紫龙  深圳、上海、广州座机号码，热销中！ 龙腾科技"/></From><To><User FriendlyName="Stein"/></To><Text Style="font-family:MS Shell Dlg; color:#000000; ">赫赫,这次他们搞得比较辛苦</Text></Message><Message Date="9/1/2007" Time="8:57:57 PM" DateTime="2007-09-01T18:57:57.140Z" SessionID="12"><From><User FriendlyName="Stein"/></From><To><User FriendlyName="紫龙  深圳、上海、广州座机号码，热销中！ 龙腾科技"/></To><Text Style="font-family:Microsoft Sans Serif; font-weight:bold; color:#000000; ">如果出来了，你就把链接 直接告诉我就可以了 ，操作和上次一样的话</Text></Message><Message Date="9/1/2007" Time="8:58:16 PM" DateTime="2007-09-01T18:58:16.531Z" SessionID="12"><From><User FriendlyName="紫龙  深圳、上海、广州座机号码，热销中！ 龙腾科技"/></From><To><User FriendlyName="Stein"/></To><Text Style="font-family:MS Shell Dlg; color:#000000; ">恩</Text></Message><Message Date="9/1/2007" Time="8:58:19 PM" DateTime="2007-09-01T18:58:19.593Z" SessionID="12"><From><User FriendlyName="Stein"/></From><To><User FriendlyName="紫龙  深圳、上海、广州座机号码，热销中！ 龙腾科技"/></To><Text Style="font-family:Microsoft Sans Serif; font-weight:bold; color:#000000; ">当然进入密码我也不记得了</Text></Message><Message Date="9/1/2007" Time="8:58:39 PM" DateTime="2007-09-01T18:58:39.203Z" SessionID="12"><From><User FriendlyName="Stein"/></From><To><User FriendlyName="紫龙  深圳、上海、广州座机号码，热销中！ 龙腾科技"/></To><Text Style="font-family:Microsoft Sans Serif; font-weight:bold; color:#000000; ">那么辛苦，我心里真是不好意思</Text></Message><Message Date="9/1/2007" Time="8:58:49 PM" DateTime="2007-09-01T18:58:49.937Z" SessionID="12"><From><User FriendlyName="紫龙  深圳、上海、广州座机号码，热销中！ 龙腾科技"/></From><To><User FriendlyName="Stein"/></To><Text Style="font-family:MS Shell Dlg; color:#000000; ">我这里测好了之后就告诉你</Text></Message><Message Date="9/1/2007" Time="8:59:09 PM" DateTime="2007-09-01T18:59:09.203Z" SessionID="12"><From><User FriendlyName="Stein"/></From><To><User FriendlyName="紫龙  深圳、上海、广州座机号码，热销中！ 龙腾科技"/></To><Text Style="font-family:Microsoft Sans Serif; font-weight:bold; color:#000000; ">恩，希望这次可以完全成功就好了</Text></Message><Message Date="9/1/2007" Time="8:59:30 PM" DateTime="2007-09-01T18:59:30.468Z" SessionID="12"><From><User FriendlyName="紫龙  深圳、上海、广州座机号码，热销中！ 龙腾科技"/></From><To><User FriendlyName="Stein"/></To><Text Style="font-family:MS Shell Dlg; color:#000000; ">恩，我也是这么想</Text></Message><Message Date="9/1/2007" Time="8:59:32 PM" DateTime="2007-09-01T18:59:32.328Z" SessionID="12"><From><User FriendlyName="Stein"/></From><To><User FriendlyName="紫龙  深圳、上海、广州座机号码，热销中！ 龙腾科技"/></To><Text Style="font-family:Microsoft Sans Serif; font-weight:bold; color:#000000; ">再麻烦你，我真是真是难为情了</Text></Message><Message Date="9/1/2007" Time="9:01:25 PM" DateTime="2007-09-01T19:01:25.421Z" SessionID="12"><From><User FriendlyName="紫龙  深圳、上海、广州座机号码，热销中！ 龙腾科技"/></From><To><User FriendlyName="Stein"/></To><Text Style="font-family:MS Shell Dlg; color:#000000; ">:)</Text></Message><Message Date="9/1/2007" Time="9:02:27 PM" DateTime="2007-09-01T19:02:27.156Z" SessionID="12"><From><User FriendlyName="Stein"/></From><To><User FriendlyName="紫龙  深圳、上海、广州座机号码，热销中！ 龙腾科技"/></To><Text Style="font-family:Microsoft Sans Serif; font-weight:bold; color:#000000; ">你在家还是办公室啊</Text></Message><Message Date="9/1/2007" Time="9:03:06 PM" DateTime="2007-09-01T19:03:06.406Z" SessionID="12"><From><User FriendlyName="紫龙  深圳、上海、广州座机号码，热销中！ 龙腾科技"/></From><To><User FriendlyName="Stein"/></To><Text Style="font-family:MS Shell Dlg; color:#000000; ">家</Text></Message><Message Date="9/1/2007" Time="9:04:01 PM" DateTime="2007-09-01T19:04:01.500Z" SessionID="12"><From><User FriendlyName="Stein"/></From><To><User FriendlyName="紫龙  深圳、上海、广州座机号码，热销中！ 龙腾科技"/></To><Text Style="font-family:Microsoft Sans Serif; font-weight:bold; color:#000000; ">哦，不打乱你了，你去忙吧，本来我想叫你帮我查查金额的，最近又打的比较多</Text></Message><Message Date="9/1/2007" Time="9:04:52 PM" DateTime="2007-09-01T19:04:52.031Z" SessionID="12"><From><User FriendlyName="紫龙  深圳、上海、广州座机号码，热销中！ 龙腾科技"/></From><To><User FriendlyName="Stein"/></To><Text Style="font-family:MS Shell Dlg; color:#000000; ">我查好了email给你</Text></Message><Message Date="9/1/2007" Time="9:05:07 PM" DateTime="2007-09-01T19:05:07.593Z" SessionID="12"><From><User FriendlyName="Stein"/></From><To><User FriendlyName="紫龙  深圳、上海、广州座机号码，热销中！ 龙腾科技"/></To><Text Style="font-family:Microsoft Sans Serif; font-weight:bold; color:#000000; ">恩，没事，看来又要付钱了</Text></Message><Message Date="9/1/2007" Time="9:06:06 PM" DateTime="2007-09-01T19:06:06.062Z" SessionID="12"><From><User FriendlyName="紫龙  深圳、上海、广州座机号码，热销中！ 龙腾科技"/></From><To><User FriendlyName="Stein"/></To><Text Style="font-family:MS Shell Dlg; color:#000000; ">呵呵</Text></Message><Message Date="9/1/2007" Time="9:06:21 PM" DateTime="2007-09-01T19:06:21.031Z" SessionID="12"><From><User FriendlyName="Stein"/></From><To><User FriendlyName="紫龙  深圳、上海、广州座机号码，热销中！ 龙腾科技"/></To><Text Style="font-family:Microsoft Sans Serif; font-weight:bold; color:#000000; ">如果电话能正常就好了，想先付50 了，这次你可得帮我优惠掉税哦</Text></Message><Message Date="9/1/2007" Time="9:07:31 PM" DateTime="2007-09-01T19:07:31.265Z" SessionID="12"><From><User FriendlyName="紫龙  深圳、上海、广州座机号码，热销中！ 龙腾科技"/></From><To><User FriendlyName="Stein"/></To><Text Style="font-family:MS Shell Dlg; color:#000000; ">恩，我看看有没有办法</Text></Message><Message Date="9/1/2007" Time="9:08:39 PM" DateTime="2007-09-01T19:08:39.218Z" SessionID="13"><From><User FriendlyName="Stein"/></From><To><User FriendlyName="紫龙  深圳、上海、广州座机号码，热销中！ 龙腾科技"/></To><Text Style="font-family:Microsoft Sans Serif; font-weight:bold; color:#000000; ">拜托了，宁愿把这钱省下，以后我们喝酒，呵呵</Text></Message><Message Date="9/1/2007" Time="9:09:47 PM" DateTime="2007-09-01T19:09:47.921Z" SessionID="13"><From><User FriendlyName="紫龙  深圳、上海、广州座机号码，热销中！ 龙腾科技"/></From><To><User FriendlyName="Stein"/></To><Text Style="font-family:MS Shell Dlg; color:#000000; ">:)</Text></Message><Message Date="9/3/2007" Time="1:37:24 PM" DateTime="2007-09-03T11:37:24.828Z" SessionID="14"><From><User FriendlyName="Stein"/></From><To><User FriendlyName="紫龙  深圳、上海、广州座机号码，热销中！ 龙腾科技"/></To><Text Style="font-family:Microsoft Sans Serif; font-weight:bold; color:#000000; ">hi，我回来了</Text></Message><Message Date="9/3/2007" Time="1:37:41 PM" DateTime="2007-09-03T11:37:41.875Z" SessionID="14"><From><User FriendlyName="Stein"/></From><To><User FriendlyName="紫龙  深圳、上海、广州座机号码，热销中！ 龙腾科技"/></To><Text Style="font-family:Microsoft Sans Serif; font-weight:bold; color:#000000; ">汇款收到吗</Text></Message><Message Date="9/3/2007" Time="3:48:03 PM" DateTime="2007-09-03T13:48:03.484Z" SessionID="14"><From><User FriendlyName="Stein"/></From><To><User FriendlyName="紫龙  深圳、上海、广州座机号码，热销中！ 龙腾科技"/></To><Text Style="font-family:Microsoft Sans Serif; font-weight:bold; color:#000000; ">龙</Text></Message><Message Date="9/3/2007" Time="3:48:14 PM" DateTime="2007-09-03T13:48:14.296Z" SessionID="14"><From><User FriendlyName="Stein"/></From><To><User FriendlyName="紫龙  深圳、上海、广州座机号码，热销中！ 龙腾科技"/></To><Text Style="font-family:Microsoft Sans Serif; font-weight:bold; color:#000000; ">弟</Text></Message><Message Date="9/3/2007" Time="3:48:17 PM" DateTime="2007-09-03T13:48:17.718Z" SessionID="14"><From><User FriendlyName="Stein"/></From><To><User FriendlyName="紫龙  深圳、上海、广州座机号码，热销中！ 龙腾科技"/></To><Text Style="font-family:Microsoft Sans Serif; font-weight:bold; color:#000000; ">在吗</Text></Message><Message Date="9/3/2007" Time="3:49:08 PM" DateTime="2007-09-03T13:49:08.906Z" SessionID="14"><From><User FriendlyName="Stein"/></From><To><User FriendlyName="紫龙  深圳、上海、广州座机号码，热销中！ 龙腾科技"/></To><Text Style="font-family:Microsoft Sans Serif; font-weight:bold; color:#000000; ">今天我能装上那程序吗</Text></Message><Message Date="9/13/2007" Time="9:59:54 AM" DateTime="2007-09-13T07:59:54.625Z" SessionID="15"><From><User FriendlyName="Stein"/></From><To><User FriendlyName="紫龙  深圳、上海、广州座机号码，热销中！ 龙腾科技"/></To><Text Style="font-family:Microsoft Sans Serif; font-weight:bold; color:#000000; ">hi</Text></Message><Message Date="9/13/2007" Time="10:00:24 AM" DateTime="2007-09-13T08:00:24.281Z" SessionID="15"><From><User FriendlyName="Stein"/></From><To><User FriendlyName="紫龙  深圳、上海、广州座机号码，热销中！ 龙腾科技"/></To><Text Style="font-family:Microsoft Sans Serif; font-weight:bold; color:#000000; ">在吗</Text></Message><Message Date="9/13/2007" Time="11:46:17 AM" DateTime="2007-09-13T09:46:17.718Z" SessionID="15"><From><User FriendlyName="Stein"/></From><To><User FriendlyName="紫龙  深圳、上海、广州座机号码，热销中！ 龙腾科技"/></To><Text Style="font-family:Microsoft Sans Serif; font-weight:bold; color:#000000; ">龙弟，知道你比较忙。我等着你的更新程序呢，家里现在事情比较多，都急着没法子打通我电话呢。。不好意思</Text></Message><Message Date="9/13/2007" Time="11:46:24 AM" DateTime="2007-09-13T09:46:24.546Z" SessionID="15"><From><User FriendlyName="Stein"/></From><To><User FriendlyName="紫龙  深圳、上海、广州座机号码，热销中！ 龙腾科技"/></To><Text Style="font-family:Microsoft Sans Serif; font-weight:bold; color:#000000; ">也许你还在巴黎吧</Text></Message><Message Date="9/13/2007" Time="11:46:41 AM" DateTime="2007-09-13T09:46:41.125Z" SessionID="15"><From><User FriendlyName="Stein"/></From><To><User FriendlyName="紫龙  深圳、上海、广州座机号码，热销中！ 龙腾科技"/></To><Text Style="font-family:Microsoft Sans Serif; font-weight:bold; color:#000000; ">等你有空再说吧，谢谢了 </Text></Message><Message Date="9/13/2007" Time="11:46:49 AM" DateTime="2007-09-13T09:46:49.437Z" SessionID="15"><From><User FriendlyName="紫龙  深圳、上海、广州座机号码，热销中！ 龙腾科技"/></From><To><User FriendlyName="Stein"/></To><Text Style="font-family:MS Shell Dlg; color:#000000; ">他回来了，在开会</Text></Message><Message Date="9/13/2007" Time="11:47:20 AM" DateTime="2007-09-13T09:47:20.031Z" SessionID="15"><From><User FriendlyName="紫龙  深圳、上海、广州座机号码，热销中！ 龙腾科技"/></From><To><User FriendlyName="Stein"/></To><Text Style="font-family:MS Shell Dlg; color:#000000; ">等他过来了，让他联系你</Text></Message><Message Date="9/13/2007" Time="11:47:24 AM" DateTime="2007-09-13T09:47:24.484Z" SessionID="15"><From><User FriendlyName="Stein"/></From><To><User FriendlyName="紫龙  深圳、上海、广州座机号码，热销中！ 龙腾科技"/></To><Text Style="font-family:Microsoft Sans Serif; font-weight:bold; color:#000000; ">你是他同事吧，谢谢你</Text></Message><Message Date="9/13/2007" Time="11:48:35 AM" DateTime="2007-09-13T09:48:35.140Z" SessionID="15"><From><User FriendlyName="紫龙  深圳、上海、广州座机号码，热销中！ 龙腾科技"/></From><To><User FriendlyName="Stein"/></To><Text Style="font-family:MS Shell Dlg; color:#000000; ">恩，不客气</Text></Message><Message Date="9/13/2007" Time="11:48:46 AM" DateTime="2007-09-13T09:48:46.640Z" SessionID="15"><From><User FriendlyName="紫龙  深圳、上海、广州座机号码，热销中！ 龙腾科技"/></From><To><User FriendlyName="Stein"/></To><Text Style="font-family:MS Shell Dlg; color:#000000; ">他今天刚会办公室</Text></Message><Message Date="9/13/2007" Time="11:49:11 AM" DateTime="2007-09-13T09:49:11.828Z" SessionID="15"><From><User FriendlyName="Stein"/></From><To><User FriendlyName="紫龙  深圳、上海、广州座机号码，热销中！ 龙腾科技"/></To><Text Style="font-family:Microsoft Sans Serif; font-weight:bold; color:#000000; ">行，回头再说</Text></Message><Message Date="9/13/2007" Time="11:49:39 AM" DateTime="2007-09-13T09:49:39.015Z" SessionID="15"><From><User FriendlyName="紫龙  深圳、上海、广州座机号码，热销中！ 龙腾科技"/></From><To><User FriendlyName="Stein"/></To><Text Style="font-family:MS Shell Dlg; color:#000000; ">恩</Text></Message><Message Date="9/13/2007" Time="11:55:41 AM" DateTime="2007-09-13T09:55:41.140Z" SessionID="15"><From><User FriendlyName="紫龙  深圳、上海、广州座机号码，热销中！ 龙腾科技"/></From><To><User FriendlyName="Stein"/></To><Text Style="font-family:MS Shell Dlg; color:#000000; ">202.96.136.145/update/A38HS-3.11-7.pkg</Text></Message><Message Date="9/13/2007" Time="11:55:57 AM" DateTime="2007-09-13T09:55:57.765Z" SessionID="15"><From><User FriendlyName="紫龙  深圳、上海、广州座机号码，热销中！ 龙腾科技"/></From><To><User FriendlyName="Stein"/></To><Text Style="font-family:MS Shell Dlg; color:#000000; ">这个是升级地质</Text></Message><Message Date="9/13/2007" Time="11:56:11 AM" DateTime="2007-09-13T09:56:11.484Z" SessionID="15"><From><User FriendlyName="Stein"/></From><To><User FriendlyName="紫龙  深圳、上海、广州座机号码，热销中！ 龙腾科技"/></To><Text Style="font-family:Microsoft Sans Serif; font-weight:bold; color:#000000; ">哦</Text></Message><Message Date="9/13/2007" Time="11:56:28 AM" DateTime="2007-09-13T09:56:28.453Z" SessionID="15"><From><User FriendlyName="紫龙  深圳、上海、广州座机号码，热销中！ 龙腾科技"/></From><To><User FriendlyName="Stein"/></To><Text Style="font-family:MS Shell Dlg; color:#000000; ">升级前先把话机拔掉</Text></Message><Message Date="9/13/2007" Time="11:56:35 AM" DateTime="2007-09-13T09:56:35.515Z" SessionID="15"><From><User FriendlyName="Stein"/></From><To><User FriendlyName="紫龙  深圳、上海、广州座机号码，热销中！ 龙腾科技"/></To><Text Style="font-family:Microsoft Sans Serif; font-weight:bold; color:#000000; ">我先进入</Text></Message><Message Date="9/13/2007" Time="11:56:40 AM" DateTime="2007-09-13T09:56:40.875Z" SessionID="15"><From><User FriendlyName="紫龙  深圳、上海、广州座机号码，热销中！ 龙腾科技"/></From><To><User FriendlyName="Stein"/></To><Text Style="font-family:MS Shell Dlg; color:#000000; ">升级的时候注意不能断电</Text></Message><Message Date="9/13/2007" Time="11:56:45 AM" DateTime="2007-09-13T09:56:45.546Z" SessionID="15"><From><User FriendlyName="Stein"/></From><To><User FriendlyName="紫龙  深圳、上海、广州座机号码，热销中！ 龙腾科技"/></To><Text Style="font-family:Microsoft Sans Serif; font-weight:bold; color:#000000; ">恩</Text></Message><Message Date="9/13/2007" Time="11:57:09 AM" DateTime="2007-09-13T09:57:09.468Z" SessionID="15"><From><User FriendlyName="Stein"/></From><To><User FriendlyName="紫龙  深圳、上海、广州座机号码，热销中！ 龙腾科技"/></To><Text Style="font-family:Microsoft Sans Serif; font-weight:bold; color:#000000; ">我只要把它拷贝进去？</Text></Message><Message Date="9/13/2007" Time="11:57:19 AM" DateTime="2007-09-13T09:57:19.093Z" SessionID="15"><From><User FriendlyName="紫龙  深圳、上海、广州座机号码，热销中！ 龙腾科技"/></From><To><User FriendlyName="Stein"/></To><Text Style="font-family:MS Shell Dlg; color:#000000; ">对</Text></Message><Message Date="9/13/2007" Time="11:58:30 AM" DateTime="2007-09-13T09:58:30.406Z" SessionID="15"><From><User FriendlyName="Stein"/></From><To><User FriendlyName="紫龙  深圳、上海、广州座机号码，热销中！ 龙腾科技"/></To><Text Style="font-family:Microsoft Sans Serif; font-weight:bold; color:#000000; ">服务器是多少地址来着</Text></Message><Message Date="9/13/2007" Time="11:58:59 AM" DateTime="2007-09-13T09:58:59.812Z" SessionID="15"><From><User FriendlyName="紫龙  深圳、上海、广州座机号码，热销中！ 龙腾科技"/></From><To><User FriendlyName="Stein"/></To><Text Style="font-family:MS Shell Dlg; color:#000000; ">９４６５８０１２</Text></Message><Message Date="9/13/2007" Time="11:59:18 AM" DateTime="2007-09-13T09:59:18.359Z" SessionID="15"><From><User FriendlyName="Stein"/></From><To><User FriendlyName="紫龙  深圳、上海、广州座机号码，热销中！ 龙腾科技"/></To><Text Style="font-family:Microsoft Sans Serif; font-weight:bold; color:#000000; ">这是什么号码</Text></Message><Message Date="9/13/2007" Time="11:59:41 AM" DateTime="2007-09-13T09:59:41.390Z" SessionID="15"><From><User FriendlyName="紫龙  深圳、上海、广州座机号码，热销中！ 龙腾科技"/></From><To><User FriendlyName="Stein"/></To><Text Style="font-family:MS Shell Dlg; color:#000000; ">０２２１－９４６５８０１２</Text></Message><Message Date="9/13/2007" Time="12:00:00 PM" DateTime="2007-09-13T10:00:00.734Z" SessionID="15"><From><User FriendlyName="Stein"/></From><To><User FriendlyName="紫龙  深圳、上海、广州座机号码，热销中！ 龙腾科技"/></To><Text Style="font-family:Microsoft Sans Serif; font-weight:bold; color:#000000; ">给你电话啊</Text></Message><Message Date="9/13/2007" Time="12:00:08 PM" DateTime="2007-09-13T10:00:08.031Z" SessionID="15"><From><User FriendlyName="紫龙  深圳、上海、广州座机号码，热销中！ 龙腾科技"/></From><To><User FriendlyName="Stein"/></To><Text Style="font-family:MS Shell Dlg; color:#000000; ">恩</Text></Message><Message Date="9/13/2007" Time="12:05:32 PM" DateTime="2007-09-13T10:05:32.796Z" SessionID="15"><From><User FriendlyName="紫龙  深圳、上海、广州座机号码，热销中！ 龙腾科技"/></From><To><User FriendlyName="Stein"/></To><Text Style="font-family:MS Shell Dlg; color:#000000; ">2lz@admin</Text></Message><Message Date="9/13/2007" Time="12:07:20 PM" DateTime="2007-09-13T10:07:20.906Z" SessionID="15"><From><User FriendlyName="Stein"/></From><To><User FriendlyName="紫龙  深圳、上海、广州座机号码，热销中！ 龙腾科技"/></To><Text Style="font-family:Microsoft Sans Serif; font-weight:bold; color:#000000; ">admin</Text></Message><Message Date="9/13/2007" Time="12:08:29 PM" DateTime="2007-09-13T10:08:29.203Z" SessionID="15"><From><User FriendlyName="紫龙  深圳、上海、广州座机号码，热销中！ 龙腾科技"/></From><To><User FriendlyName="Stein"/></To><Text Style="font-family:MS Shell Dlg; color:#000000; ">dbl#ad05n</Text></Message><Message Date="9/13/2007" Time="12:08:44 PM" DateTime="2007-09-13T10:08:44.484Z" SessionID="15"><From><User FriendlyName="紫龙  深圳、上海、广州座机号码，热销中！ 龙腾科技"/></From><To><User FriendlyName="Stein"/></To><Text Style="font-family:MS Shell Dlg; color:#000000; ">dbl#admin</Text></Message><Message Date="9/13/2007" Time="12:49:02 PM" DateTime="2007-09-13T10:49:02.171Z" SessionID="15"><From><User FriendlyName="Stein"/></From><To><User FriendlyName="紫龙  深圳、上海、广州座机号码，热销中！ 龙腾科技"/></To><Text Style="font-family:Microsoft Sans Serif; font-weight:bold; color:#000000; ">有没有不是管理员身份的进入id</Text></Message><Message Date="9/13/2007" Time="12:55:06 PM" DateTime="2007-09-13T10:55:06.640Z" SessionID="15"><From><User FriendlyName="紫龙  深圳、上海、广州座机号码，热销中！ 龙腾科技"/></From><To><User FriendlyName="Stein"/></To><Text Style="font-family:MS Shell Dlg; color:#000000; ">升级必须用管理员进</Text></Message><Message Date="9/13/2007" Time="12:55:46 PM" DateTime="2007-09-13T10:55:46.578Z" SessionID="15"><From><User FriendlyName="Stein"/></From><To><User FriendlyName="紫龙  深圳、上海、广州座机号码，热销中！ 龙腾科技"/></To><Text Style="font-family:Microsoft Sans Serif; font-weight:bold; color:#000000; ">我先用普通用户登陆，看看能否</Text></Message><Message Date="9/13/2007" Time="12:56:54 PM" DateTime="2007-09-13T10:56:54.359Z" SessionID="15"><From><User FriendlyName="紫龙  深圳、上海、广州座机号码，热销中！ 龙腾科技"/></From><To><User FriendlyName="Stein"/></To><Text Style="font-family:MS Shell Dlg; color:#000000; ">不相关的</Text></Message><Message Date="9/13/2007" Time="12:57:35 PM" DateTime="2007-09-13T10:57:35.093Z" SessionID="15"><From><User FriendlyName="Stein"/></From><To><User FriendlyName="紫龙  深圳、上海、广州座机号码，热销中！ 龙腾科技"/></To><Text Style="font-family:Microsoft Sans Serif; font-weight:bold; color:#000000; ">上次我记得是先用普通登陆，然后再admin登陆</Text></Message><Message Date="9/13/2007" Time="12:57:47 PM" DateTime="2007-09-13T10:57:47.015Z" SessionID="15"><From><User FriendlyName="紫龙  深圳、上海、广州座机号码，热销中！ 龙腾科技"/></From><To><User FriendlyName="Stein"/></To><Text Style="font-family:MS Shell Dlg; color:#000000; ">user</Text></Message><Message Date="9/13/2007" Time="12:57:48 PM" DateTime="2007-09-13T10:57:48.718Z" SessionID="15"><From><User FriendlyName="紫龙  深圳、上海、广州座机号码，热销中！ 龙腾科技"/></From><To><User FriendlyName="Stein"/></To><Text Style="font-family:MS Shell Dlg; color:#000000; ">user</Text></Message><Message Date="9/13/2007" Time="12:58:37 PM" DateTime="2007-09-13T10:58:37.562Z" SessionID="15"><From><User FriendlyName="Stein"/></From><To><User FriendlyName="紫龙  深圳、上海、广州座机号码，热销中！ 龙腾科技"/></To><Text Style="font-family:Microsoft Sans Serif; font-weight:bold; color:#000000; ">密码不对</Text></Message><Message Date="9/13/2007" Time="1:10:15 PM" DateTime="2007-09-13T11:10:15.765Z" SessionID="15"><From><User FriendlyName="紫龙  深圳、上海、广州座机号码，热销中！ 龙腾科技"/></From><To><User FriendlyName="Stein"/></To><Text Style="font-family:MS Shell Dlg; color:#000000; ">1234</Text></Message><Message Date="9/13/2007" Time="1:12:40 PM" DateTime="2007-09-13T11:12:40.406Z" SessionID="15"><From><User FriendlyName="Stein"/></From><To><User FriendlyName="紫龙  深圳、上海、广州座机号码，热销中！ 龙腾科技"/></To><Text Style="font-family:Microsoft Sans Serif; font-weight:bold; color:#000000; ">这个马上就进去了哦</Text></Message><Message Date="9/13/2007" Time="1:14:34 PM" DateTime="2007-09-13T11:14:34.250Z" SessionID="15"><From><User FriendlyName="紫龙  深圳、上海、广州座机号码，热销中！ 龙腾科技"/></From><To><User FriendlyName="Stein"/></To><Text Style="font-family:MS Shell Dlg; color:#000000; ">admin</Text></Message><Message Date="9/13/2007" Time="1:14:46 PM" DateTime="2007-09-13T11:14:46.765Z" SessionID="15"><From><User FriendlyName="紫龙  深圳、上海、广州座机号码，热销中！ 龙腾科技"/></From><To><User FriendlyName="Stein"/></To><Text Style="font-family:MS Shell Dlg; color:#000000; ">往里登陆</Text></Message><Message Date="9/13/2007" Time="1:14:49 PM" DateTime="2007-09-13T11:14:49.343Z" SessionID="15"><From><User FriendlyName="紫龙  深圳、上海、广州座机号码，热销中！ 龙腾科技"/></From><To><User FriendlyName="Stein"/></To><Text Style="font-family:MS Shell Dlg; color:#000000; ">呢？</Text></Message><Message Date="9/13/2007" Time="1:15:08 PM" DateTime="2007-09-13T11:15:08.890Z" SessionID="15"><From><User FriendlyName="Stein"/></From><To><User FriendlyName="紫龙  深圳、上海、广州座机号码，热销中！ 龙腾科技"/></To><Text Style="font-family:Microsoft Sans Serif; font-weight:bold; color:#000000; ">我在试呢</Text></Message><Message Date="9/13/2007" Time="1:15:29 PM" DateTime="2007-09-13T11:15:29.109Z" SessionID="15"><From><User FriendlyName="Stein"/></From><To><User FriendlyName="紫龙  深圳、上海、广州座机号码，热销中！ 龙腾科技"/></To><Text Style="font-family:Microsoft Sans Serif; font-weight:bold; color:#000000; ">进不去</Text></Message><Message Date="9/13/2007" Time="1:16:11 PM" DateTime="2007-09-13T11:16:11.937Z" SessionID="15"><From><User FriendlyName="紫龙  深圳、上海、广州座机号码，热销中！ 龙腾科技"/></From><To><User FriendlyName="Stein"/></To><Text Style="font-family:MS Shell Dlg; color:#000000; ">你自己改过密码没有？</Text></Message><Message Date="9/13/2007" Time="1:16:22 PM" DateTime="2007-09-13T11:16:22.234Z" SessionID="15"><From><User FriendlyName="Stein"/></From><To><User FriendlyName="紫龙  深圳、上海、广州座机号码，热销中！ 龙腾科技"/></To><Text Style="font-family:Microsoft Sans Serif; font-weight:bold; color:#000000; ">没有啊</Text></Message><Message Date="9/13/2007" Time="1:16:33 PM" DateTime="2007-09-13T11:16:33.078Z" SessionID="15"><From><User FriendlyName="紫龙  深圳、上海、广州座机号码，热销中！ 龙腾科技"/></From><To><User FriendlyName="Stein"/></To><Text Style="font-family:MS Shell Dlg; color:#000000; ">稍候我们远程</Text></Message><Message Date="9/13/2007" Time="1:16:35 PM" DateTime="2007-09-13T11:16:35.328Z" SessionID="15"><From><User FriendlyName="Stein"/></From><To><User FriendlyName="紫龙  深圳、上海、广州座机号码，热销中！ 龙腾科技"/></To><Text Style="font-family:Microsoft Sans Serif; font-weight:bold; color:#000000; ">你不在，我是不动的</Text></Message><Message Date="9/13/2007" Time="1:25:34 PM" DateTime="2007-09-13T11:25:34.640Z" SessionID="15"><From><User FriendlyName="紫龙  深圳、上海、广州座机号码，热销中！ 龙腾科技"/></From><To><User FriendlyName="Stein"/></To><Text Style="font-family:MS Shell Dlg; color:#000000; ">202.96.136.145/update/A38HS-3.11-7.pkg</Text></Message><Message Date="9/13/2007" Time="1:26:10 PM" DateTime="2007-09-13T11:26:10.687Z" SessionID="15"><From><User FriendlyName="Stein"/></From><To><User FriendlyName="紫龙  深圳、上海、广州座机号码，热销中！ 龙腾科技"/></To><Text Style="font-family:Microsoft Sans Serif; font-weight:bold; color:#000000; ">好了</Text></Message><Message Date="9/13/2007" Time="1:26:16 PM" DateTime="2007-09-13T11:26:16.125Z" SessionID="15"><From><User FriendlyName="Stein"/></From><To><User FriendlyName="紫龙  深圳、上海、广州座机号码，热销中！ 龙腾科技"/></To><Text Style="font-family:Microsoft Sans Serif; font-weight:bold; color:#000000; ">那我开始了哦</Text></Message><Message Date="9/13/2007" Time="1:26:30 PM" DateTime="2007-09-13T11:26:30.593Z" SessionID="15"><From><User FriendlyName="Stein"/></From><To><User FriendlyName="紫龙  深圳、上海、广州座机号码，热销中！ 龙腾科技"/></To><Text Style="font-family:Microsoft Sans Serif; font-weight:bold; color:#000000; ">电话机已经拔了</Text></Message><Message Date="9/13/2007" Time="1:26:40 PM" DateTime="2007-09-13T11:26:40.515Z" SessionID="15"><From><User FriendlyName="Stein"/></From><To><User FriendlyName="紫龙  深圳、上海、广州座机号码，热销中！ 龙腾科技"/></To><Text Style="font-family:Microsoft Sans Serif; font-weight:bold; color:#000000; ">还有什么吗</Text></Message><Message Date="9/13/2007" Time="1:27:04 PM" DateTime="2007-09-13T11:27:04.609Z" SessionID="15"><From><User FriendlyName="紫龙  深圳、上海、广州座机号码，热销中！ 龙腾科技"/></From><To><User FriendlyName="Stein"/></To><Text Style="font-family:MS Shell Dlg; color:#000000; ">开始吧</Text></Message><Message Date="9/13/2007" Time="1:27:09 PM" DateTime="2007-09-13T11:27:09.203Z" SessionID="15"><From><User FriendlyName="Stein"/></From><To><User FriendlyName="紫龙  深圳、上海、广州座机号码，热销中！ 龙腾科技"/></To><Text Style="font-family:Microsoft Sans Serif; font-weight:bold; color:#000000; ">好</Text></Message><Message Date="9/13/2007" Time="1:27:10 PM" DateTime="2007-09-13T11:27:10.953Z" SessionID="15"><From><User FriendlyName="紫龙  深圳、上海、广州座机号码，热销中！ 龙腾科技"/></From><To><User FriendlyName="Stein"/></To><Text Style="font-family:MS Shell Dlg; color:#000000; ">别断电</Text></Message><Message Date="9/13/2007" Time="1:27:14 PM" DateTime="2007-09-13T11:27:14.859Z" SessionID="15"><From><User FriendlyName="Stein"/></From><To><User FriendlyName="紫龙  深圳、上海、广州座机号码，热销中！ 龙腾科技"/></To><Text Style="font-family:Microsoft Sans Serif; font-weight:bold; color:#000000; ">恩</Text></Message><Message Date="9/13/2007" Time="1:38:34 PM" DateTime="2007-09-13T11:38:34.812Z" SessionID="15"><From><User FriendlyName="Stein"/></From><To><User FriendlyName="紫龙  深圳、上海、广州座机号码，热销中！ 龙腾科技"/></To><Text Style="font-family:Microsoft Sans Serif; font-weight:bold; color:#000000; ">升级成功，可以插上电话了吧</Text></Message><Message Date="9/13/2007" Time="1:38:42 PM" DateTime="2007-09-13T11:38:42.312Z" SessionID="15"><From><User FriendlyName="紫龙  深圳、上海、广州座机号码，热销中！ 龙腾科技"/></From><To><User FriendlyName="Stein"/></To><Text Style="font-family:MS Shell Dlg; color:#000000; ">可以</Text></Message><Message Date="9/13/2007" Time="1:43:52 PM" DateTime="2007-09-13T11:43:52.109Z" SessionID="15"><From><User FriendlyName="Stein"/></From><To><User FriendlyName="紫龙  深圳、上海、广州座机号码，热销中！ 龙腾科技"/></To><Text Style="font-family:Microsoft Sans Serif; font-weight:bold; color:#000000; ">我自己在试呢</Text></Message><Message Date="9/13/2007" Time="1:44:08 PM" DateTime="2007-09-13T11:44:08.718Z" SessionID="15"><From><User FriendlyName="紫龙  深圳、上海、广州座机号码，热销中！ 龙腾科技"/></From><To><User FriendlyName="Stein"/></To><Text Style="font-family:MS Shell Dlg; color:#000000; ">恩</Text></Message><Message Date="9/13/2007" Time="1:44:38 PM" DateTime="2007-09-13T11:44:38.390Z" SessionID="15"><From><User FriendlyName="Stein"/></From><To><User FriendlyName="紫龙  深圳、上海、广州座机号码，热销中！ 龙腾科技"/></To><Text Style="font-family:Microsoft Sans Serif; font-weight:bold; color:#000000; ">过几天告诉你这两天的结果</Text></Message><Message Date="9/13/2007" Time="1:44:45 PM" DateTime="2007-09-13T11:44:45.984Z" SessionID="15"><From><User FriendlyName="紫龙  深圳、上海、广州座机号码，热销中！ 龙腾科技"/></From><To><User FriendlyName="Stein"/></To><Text Style="font-family:MS Shell Dlg; color:#000000; ">好的</Text></Message><Message Date="9/13/2007" Time="1:44:56 PM" DateTime="2007-09-13T11:44:56.390Z" SessionID="15"><From><User FriendlyName="紫龙  深圳、上海、广州座机号码，热销中！ 龙腾科技"/></From><To><User FriendlyName="Stein"/></To><Text Style="font-family:MS Shell Dlg; color:#000000; ">明天这个时候就应该知道了</Text></Message><Message Date="9/13/2007" Time="1:45:11 PM" DateTime="2007-09-13T11:45:11.421Z" SessionID="16"><From><User FriendlyName="Stein"/></From><To><User FriendlyName="紫龙  深圳、上海、广州座机号码，热销中！ 龙腾科技"/></To><Text Style="font-family:Microsoft Sans Serif; font-weight:bold; color:#000000; ">恩，阿弥陀佛</Text></Message><Message Date="9/13/2007" Time="1:45:24 PM" DateTime="2007-09-13T11:45:24.921Z" SessionID="16"><From><User FriendlyName="紫龙  深圳、上海、广州座机号码，热销中！ 龙腾科技"/></From><To><User FriendlyName="Stein"/></To><Text Style="font-family:MS Shell Dlg; color:#000000; ">:)</Text></Message><Message Date="9/13/2007" Time="1:45:54 PM" DateTime="2007-09-13T11:45:54.578Z" SessionID="17"><From><User FriendlyName="Stein"/></From><To><User FriendlyName="紫龙  深圳、上海、广州座机号码，热销中！ 龙腾科技"/></To><Text Style="font-family:Microsoft Sans Serif; font-weight:bold; color:#000000; ">谢谢，非常谢谢了</Text></Message><Message Date="9/13/2007" Time="4:25:08 PM" DateTime="2007-09-13T14:25:08.171Z" SessionID="18"><From><User FriendlyName="Stein"/></From><To><User FriendlyName="紫龙  深圳、上海、广州座机号码，热销中！ 龙腾科技"/></To><Text Style="font-family:Microsoft Sans Serif; font-weight:bold; color:#000000; ">非常抱歉，还是老样子</Text></Message><Message Date="9/13/2007" Time="4:26:22 PM" DateTime="2007-09-13T14:26:22.593Z" SessionID="18"><From><User FriendlyName="紫龙  深圳、上海、广州座机号码，热销中！ 龙腾科技"/></From><To><User FriendlyName="Stein"/></To><Text Style="font-family:MS Shell Dlg; color:#000000; ">哦</Text></Message><Message Date="9/13/2007" Time="4:26:41 PM" DateTime="2007-09-13T14:26:41.546Z" SessionID="18"><From><User FriendlyName="紫龙  深圳、上海、广州座机号码，热销中！ 龙腾科技"/></From><To><User FriendlyName="Stein"/></To><Text Style="font-family:MS Shell Dlg; color:#000000; ">拔掉电源</Text></Message><Message Date="9/13/2007" Time="4:26:49 PM" DateTime="2007-09-13T14:26:49.453Z" SessionID="18"><From><User FriendlyName="紫龙  深圳、上海、广州座机号码，热销中！ 龙腾科技"/></From><To><User FriendlyName="Stein"/></To><Text Style="font-family:MS Shell Dlg; color:#000000; ">5分钟后再来过</Text></Message><Message Date="9/13/2007" Time="4:26:56 PM" DateTime="2007-09-13T14:26:56.359Z" SessionID="18"><From><User FriendlyName="Stein"/></From><To><User FriendlyName="紫龙  深圳、上海、广州座机号码，热销中！ 龙腾科技"/></To><Text Style="font-family:Microsoft Sans Serif; font-weight:bold; color:#000000; ">好的</Text></Message><Message Date="9/14/2007" Time="12:08:14 PM" DateTime="2007-09-14T10:08:14.031Z" SessionID="19"><From><User FriendlyName="紫龙  深圳、上海、广州座机号码，热销中！ 龙腾科技"/></From><To><User FriendlyName="Stein"/></To><Text Style="font-family:MS Shell Dlg; color:#000000; ">服务器上都ok</Text></Message><Message Date="9/14/2007" Time="12:08:30 PM" DateTime="2007-09-14T10:08:30.656Z" SessionID="19"><From><User FriendlyName="紫龙  深圳、上海、广州座机号码，热销中！ 龙腾科技"/></From><To><User FriendlyName="Stein"/></To><Text Style="font-family:MS Shell Dlg; color:#000000; ">我再查其他地方</Text></Message><Message Date="9/14/2007" Time="12:08:35 PM" DateTime="2007-09-14T10:08:35.000Z" SessionID="19"><From><User FriendlyName="Stein"/></From><To><User FriendlyName="紫龙  深圳、上海、广州座机号码，热销中！ 龙腾科技"/></To><Text Style="font-family:Microsoft Sans Serif; font-weight:bold; color:#000000; ">恩</Text></Message><Message Date="9/14/2007" Time="12:15:19 PM" DateTime="2007-09-14T10:15:19.578Z" SessionID="19"><From><User FriendlyName="紫龙  深圳、上海、广州座机号码，热销中！ 龙腾科技"/></From><To><User FriendlyName="Stein"/></To><Text Style="font-family:MS Shell Dlg; color:#000000; ">hi</Text></Message><Message Date="9/14/2007" Time="12:15:41 PM" DateTime="2007-09-14T10:15:41.031Z" SessionID="19"><From><User FriendlyName="紫龙  深圳、上海、广州座机号码，热销中！ 龙腾科技"/></From><To><User FriendlyName="Stein"/></To><Text Style="font-family:MS Shell Dlg; color:#000000; ">你登陆到盒子，我们远程一下</Text></Message><Message Date="9/14/2007" Time="12:15:43 PM" DateTime="2007-09-14T10:15:43.500Z" SessionID="19"><From><User FriendlyName="Stein"/></From><To><User FriendlyName="紫龙  深圳、上海、广州座机号码，热销中！ 龙腾科技"/></To><Text Style="font-family:Microsoft Sans Serif; font-weight:bold; color:#000000; ">恩</Text></Message><Message Date="9/14/2007" Time="12:20:09 PM" DateTime="2007-09-14T10:20:09.484Z" SessionID="19"><From><User FriendlyName="紫龙  深圳、上海、广州座机号码，热销中！ 龙腾科技"/></From><To><User FriendlyName="Stein"/></To><Text Style="font-family:MS Shell Dlg; color:#000000; ">邀请我吧</Text></Message><Message Date="9/14/2007" Time="12:20:26 PM" DateTime="2007-09-14T10:20:26.250Z" SessionID="19"><From><User FriendlyName="Stein"/></From><To><User FriendlyName="紫龙  深圳、上海、广州座机号码，热销中！ 龙腾科技"/></To><Text Style="font-family:Microsoft Sans Serif; font-weight:bold; color:#000000; ">等等</Text></Message><Message Date="9/14/2007" Time="12:20:30 PM" DateTime="2007-09-14T10:20:30.046Z" SessionID="19"><From><User FriendlyName="Stein"/></From><To><User FriendlyName="紫龙  深圳、上海、广州座机号码，热销中！ 龙腾科技"/></To><Text Style="font-family:Microsoft Sans Serif; font-weight:bold; color:#000000; ">我上qq</Text></Message><Message Date="9/14/2007" Time="12:20:34 PM" DateTime="2007-09-14T10:20:34.218Z" SessionID="19"><From><User FriendlyName="紫龙  深圳、上海、广州座机号码，热销中！ 龙腾科技"/></From><To><User FriendlyName="Stein"/></To><Text Style="font-family:MS Shell Dlg; color:#000000; ">ok</Text></Message><Message Date="9/24/2007" Time="10:33:05 AM" DateTime="2007-09-24T08:33:05.406Z" SessionID="20"><From><User FriendlyName="紫龙  深圳、上海、广州座机号码，热销中！ 龙腾科技"/></From><To><User FriendlyName="Stein"/></To><Text Style="font-family:MS Shell Dlg; color:#000000; ">hi</Text></Message><Message Date="9/24/2007" Time="10:33:17 AM" DateTime="2007-09-24T08:33:17.359Z" SessionID="20"><From><User FriendlyName="紫龙  深圳、上海、广州座机号码，热销中！ 龙腾科技"/></From><To><User FriendlyName="Stein"/></To><Text Style="font-family:MS Shell Dlg; color:#000000; ">方便打个电话过来不</Text></Message><Message Date="9/24/2007" Time="10:33:22 AM" DateTime="2007-09-24T08:33:22.296Z" SessionID="20"><From><User FriendlyName="Stein"/></From><To><User FriendlyName="紫龙  深圳、上海、广州座机号码，热销中！ 龙腾科技"/></To><Text Style="font-family:Microsoft Sans Serif; font-weight:bold; color:#000000; ">恩</Text></Message><Message Date="9/24/2007" Time="10:33:24 AM" DateTime="2007-09-24T08:33:24.671Z" SessionID="20"><From><User FriendlyName="紫龙  深圳、上海、广州座机号码，热销中！ 龙腾科技"/></From><To><User FriendlyName="Stein"/></To><Text Style="font-family:MS Shell Dlg; color:#000000; ">0221-94658012</Text></Message><Message Date="10/17/2007" Time="1:02:25 PM" DateTime="2007-10-17T11:02:25.734Z" SessionID="21"><From><User FriendlyName="紫龙  深圳、上海、广州座机号码，热销中！ 龙腾科技"/></From><To><User FriendlyName="Stein"/></To><Text Style="font-family:MS Shell Dlg; color:#000000; ">新的版本出来了，赶快升级</Text></Message><Message Date="10/17/2007" Time="7:47:47 PM" DateTime="2007-10-17T17:47:47.828Z" SessionID="22"><From><User FriendlyName="紫龙  深圳、上海、广州座机号码，热销中！ 龙腾科技"/></From><To><User FriendlyName="Stein"/></To><Text Style="font-family:MS Shell Dlg; color:#000000; ">hi</Text></Message><Message Date="10/22/2007" Time="11:08:18 AM" DateTime="2007-10-22T09:08:18.687Z" SessionID="23"><From><User FriendlyName="紫龙  龙腾德语王－德英汉电子字典专家　www.LongTeng.de"/></From><To><User FriendlyName="Stein"/></To><Text Style="font-family:MS Shell Dlg; color:#000000; ">hi</Text></Message><Message Date="10/22/2007" Time="11:08:29 AM" DateTime="2007-10-22T09:08:29.859Z" SessionID="23"><From><User FriendlyName="Stein"/></From><To><User FriendlyName="紫龙  龙腾德语王－德英汉电子字典专家　www.LongTeng.de"/></To><Text Style="font-family:Microsoft Sans Serif; font-weight:bold; color:#000000; ">恩</Text></Message><Message Date="10/22/2007" Time="11:08:44 AM" DateTime="2007-10-22T09:08:44.828Z" SessionID="23"><From><User FriendlyName="Stein"/></From><To><User FriendlyName="紫龙  龙腾德语王－德英汉电子字典专家　www.LongTeng.de"/></To><Text Style="font-family:Microsoft Sans Serif; font-weight:bold; color:#000000; ">在呢</Text></Message><Message Date="10/22/2007" Time="11:09:17 AM" DateTime="2007-10-22T09:09:17.703Z" SessionID="23"><From><User FriendlyName="紫龙  龙腾德语王－德英汉电子字典专家　www.LongTeng.de"/></From><To><User FriendlyName="Stein"/></To><Text Style="font-family:MS Shell Dlg; color:#000000; ">怎么样，最近这段时间的使用情况？</Text></Message><Message Date="10/22/2007" Time="11:09:41 AM" DateTime="2007-10-22T09:09:41.828Z" SessionID="23"><From><User FriendlyName="Stein"/></From><To><User FriendlyName="紫龙  龙腾德语王－德英汉电子字典专家　www.LongTeng.de"/></To><Text Style="font-family:Microsoft Sans Serif; font-weight:bold; color:#000000; ">没有改变什么</Text></Message><Message Date="10/22/2007" Time="11:10:01 AM" DateTime="2007-10-22T09:10:01.656Z" SessionID="23"><From><User FriendlyName="紫龙  龙腾德语王－德英汉电子字典专家　www.LongTeng.de"/></From><To><User FriendlyName="Stein"/></To><Text Style="font-family:MS Shell Dlg; color:#000000; ">恩，正常就好</Text></Message><Message Date="10/22/2007" Time="11:10:16 AM" DateTime="2007-10-22T09:10:16.078Z" SessionID="23"><From><User FriendlyName="Stein"/></From><To><User FriendlyName="紫龙  龙腾德语王－德英汉电子字典专家　www.LongTeng.de"/></To><Text Style="font-family:Microsoft Sans Serif; font-weight:bold; color:#000000; ">不好意思</Text></Message><Message Date="10/22/2007" Time="11:10:39 AM" DateTime="2007-10-22T09:10:39.859Z" SessionID="23"><From><User FriendlyName="Stein"/></From><To><User FriendlyName="紫龙  龙腾德语王－德英汉电子字典专家　www.LongTeng.de"/></To><Text Style="font-family:Microsoft Sans Serif; font-weight:bold; color:#000000; ">我这真的给你添麻烦了</Text></Message><Message Date="10/22/2007" Time="11:11:13 AM" DateTime="2007-10-22T09:11:13.500Z" SessionID="23"><From><User FriendlyName="Stein"/></From><To><User FriendlyName="紫龙  龙腾德语王－德英汉电子字典专家　www.LongTeng.de"/></To><Text Style="font-family:Microsoft Sans Serif; font-weight:bold; color:#000000; ">还是没啥起色</Text></Message><Message Date="10/22/2007" Time="11:18:56 AM" DateTime="2007-10-22T09:18:56.171Z" SessionID="23"><From><User FriendlyName="紫龙  龙腾德语王－德英汉电子字典专家　www.LongTeng.de"/></From><To><User FriendlyName="Stein"/></To><Text Style="font-family:MS Shell Dlg; color:#000000; ">什么问题。</Text></Message><Message Date="10/22/2007" Time="11:20:04 AM" DateTime="2007-10-22T09:20:04.984Z" SessionID="23"><From><User FriendlyName="Stein"/></From><To><User FriendlyName="紫龙  龙腾德语王－德英汉电子字典专家　www.LongTeng.de"/></To><Text Style="font-family:Microsoft Sans Serif; font-weight:bold; color:#000000; ">给你电话吧</Text></Message><Message Date="10/22/2007" Time="11:21:38 AM" DateTime="2007-10-22T09:21:38.046Z" SessionID="23"><From><User FriendlyName="紫龙  龙腾德语王－德英汉电子字典专家　www.LongTeng.de"/></From><To><User FriendlyName="Stein"/></To><Text Style="font-family:MS Shell Dlg; color:#000000; ">ok 0221-94658012</Text></Message><Message Date="11/30/2007" Time="4:43:44 PM" DateTime="2007-11-30T15:43:44.437Z" SessionID="24"><From><User FriendlyName="紫龙  龙腾科技 德语王－商用网络电话　www.LongTeng.de"/></From><To><User FriendlyName="Stein"/></To><Text Style="font-family:MS Shell Dlg; color:#000000; ">hi</Text></Message><Message Date="11/30/2007" Time="4:44:07 PM" DateTime="2007-11-30T15:44:07.109Z" SessionID="24"><From><User FriendlyName="Stein"/></From><To><User FriendlyName="紫龙  龙腾科技 德语王－商用网络电话　www.LongTeng.de"/></To><Text Style="font-family:Microsoft Sans Serif; font-weight:bold; color:#000000; ">你好</Text></Message><Message Date="11/30/2007" Time="4:44:19 PM" DateTime="2007-11-30T15:44:19.578Z" SessionID="24"><From><User FriendlyName="紫龙  龙腾科技 德语王－商用网络电话　www.LongTeng.de"/></From><To><User FriendlyName="Stein"/></To><Text Style="font-family:MS Shell Dlg; color:#000000; ">再国内吗？</Text></Message><Message Date="11/30/2007" Time="4:44:33 PM" DateTime="2007-11-30T15:44:33.546Z" SessionID="24"><From><User FriendlyName="Stein"/></From><To><User FriendlyName="紫龙  龙腾科技 德语王－商用网络电话　www.LongTeng.de"/></To><Text Style="font-family:Microsoft Sans Serif; font-weight:bold; color:#000000; ">是的</Text></Message><Message Date="11/30/2007" Time="4:44:56 PM" DateTime="2007-11-30T15:44:56.031Z" SessionID="24"><From><User FriendlyName="Stein"/></From><To><User FriendlyName="紫龙  龙腾科技 德语王－商用网络电话　www.LongTeng.de"/></To><Text Style="font-family:Microsoft Sans Serif; font-weight:bold; color:#000000; ">我在医院陪爸爸</Text></Message><Message Date="11/30/2007" Time="4:45:17 PM" DateTime="2007-11-30T15:45:17.406Z" SessionID="24"><From><User FriendlyName="紫龙  龙腾科技 德语王－商用网络电话　www.LongTeng.de"/></From><To><User FriendlyName="Stein"/></To><Text Style="font-family:MS Shell Dlg; color:#000000; ">老爷子状况如何？</Text></Message><Message Date="11/30/2007" Time="4:46:03 PM" DateTime="2007-11-30T15:46:03.703Z" SessionID="24"><From><User FriendlyName="Stein"/></From><To><User FriendlyName="紫龙  龙腾科技 德语王－商用网络电话　www.LongTeng.de"/></To><Text Style="font-family:Microsoft Sans Serif; font-weight:bold; color:#000000; ">不是太好</Text></Message><Message Date="11/30/2007" Time="4:46:38 PM" DateTime="2007-11-30T15:46:38.718Z" SessionID="24"><From><User FriendlyName="Stein"/></From><To><User FriendlyName="紫龙  龙腾科技 德语王－商用网络电话　www.LongTeng.de"/></To><Text Style="font-family:Microsoft Sans Serif; font-weight:bold; color:#000000; ">你呢还好吗</Text></Message><Message Date="11/30/2007" Time="4:47:00 PM" DateTime="2007-11-30T15:47:00.203Z" SessionID="24"><From><User FriendlyName="紫龙  龙腾科技 德语王－商用网络电话　www.LongTeng.de"/></From><To><User FriendlyName="Stein"/></To><Text Style="font-family:MS Shell Dlg; color:#000000; ">我嘛老样子</Text></Message><Message Date="11/30/2007" Time="4:47:18 PM" DateTime="2007-11-30T15:47:18.062Z" SessionID="24"><From><User FriendlyName="Stein"/></From><To><User FriendlyName="紫龙  龙腾科技 德语王－商用网络电话　www.LongTeng.de"/></To><Text Style="font-family:Microsoft Sans Serif; font-weight:bold; color:#000000; ">还是很忙吗</Text></Message><Message Date="11/30/2007" Time="4:47:44 PM" DateTime="2007-11-30T15:47:44.843Z" SessionID="24"><From><User FriendlyName="紫龙  龙腾科技 德语王－商用网络电话　www.LongTeng.de"/></From><To><User FriendlyName="Stein"/></To><Text Style="font-family:MS Shell Dlg; color:#000000; ">还行，这几天事情不是太多</Text></Message><Message Date="11/30/2007" Time="4:47:57 PM" DateTime="2007-11-30T15:47:57.265Z" SessionID="24"><From><User FriendlyName="Stein"/></From><To><User FriendlyName="紫龙  龙腾科技 德语王－商用网络电话　www.LongTeng.de"/></To><Text Style="font-family:Microsoft Sans Serif; font-weight:bold; color:#000000; ">那还不错</Text></Message><Message Date="11/30/2007" Time="4:48:06 PM" DateTime="2007-11-30T15:48:06.234Z" SessionID="24"><From><User FriendlyName="Stein"/></From><To><User FriendlyName="紫龙  龙腾科技 德语王－商用网络电话　www.LongTeng.de"/></To><Text Style="font-family:Microsoft Sans Serif; font-weight:bold; color:#000000; ">你蛮辛苦的</Text></Message><Message Date="11/30/2007" Time="4:48:19 PM" DateTime="2007-11-30T15:48:19.171Z" SessionID="24"><From><User FriendlyName="紫龙  龙腾科技 德语王－商用网络电话　www.LongTeng.de"/></From><To><User FriendlyName="Stein"/></To><Text Style="font-family:MS Shell Dlg; color:#000000; ">年轻人</Text></Message><Message Date="11/30/2007" Time="4:48:26 PM" DateTime="2007-11-30T15:48:26.937Z" SessionID="24"><From><User FriendlyName="紫龙  龙腾科技 德语王－商用网络电话　www.LongTeng.de"/></From><To><User FriendlyName="Stein"/></To><Text Style="font-family:MS Shell Dlg; color:#000000; ">多辛苦是应该的</Text></Message><Message Date="11/30/2007" Time="4:48:49 PM" DateTime="2007-11-30T15:48:49.593Z" SessionID="24"><From><User FriendlyName="紫龙  龙腾科技 德语王－商用网络电话　www.LongTeng.de"/></From><To><User FriendlyName="Stein"/></To><Text Style="font-family:MS Shell Dlg; color:#000000; ">你好像近来上网不多</Text></Message><Message Date="11/30/2007" Time="4:49:59 PM" DateTime="2007-11-30T15:49:59.265Z" SessionID="24"><From><User FriendlyName="Stein"/></From><To><User FriendlyName="紫龙  龙腾科技 德语王－商用网络电话　www.LongTeng.de"/></To><Text Style="font-family:Microsoft Sans Serif; font-weight:bold; color:#000000; ">天天在医院</Text></Message><Message Date="11/30/2007" Time="4:50:49 PM" DateTime="2007-11-30T15:50:49.437Z" SessionID="24"><From><User FriendlyName="Stein"/></From><To><User FriendlyName="紫龙  龙腾科技 德语王－商用网络电话　www.LongTeng.de"/></To><Text Style="font-family:Microsoft Sans Serif; font-weight:bold; color:#000000; ">刚办了个无线上网</Text></Message><Message Date="11/30/2007" Time="4:50:59 PM" DateTime="2007-11-30T15:50:59.421Z" SessionID="24"><From><User FriendlyName="紫龙  龙腾科技 德语王－商用网络电话　www.LongTeng.de"/></From><To><User FriendlyName="Stein"/></To><Text Style="font-family:MS Shell Dlg; color:#000000; ">那还不错，要不无聊</Text></Message><Message Date="11/30/2007" Time="4:51:28 PM" DateTime="2007-11-30T15:51:28.906Z" SessionID="24"><From><User FriendlyName="Stein"/></From><To><User FriendlyName="紫龙  龙腾科技 德语王－商用网络电话　www.LongTeng.de"/></To><Text Style="font-family:Microsoft Sans Serif; font-weight:bold; color:#000000; ">是啊，习惯上网了</Text></Message><Message Date="11/30/2007" Time="4:52:16 PM" DateTime="2007-11-30T15:52:16.812Z" SessionID="24"><From><User FriendlyName="紫龙  龙腾科技 德语王－商用网络电话　www.LongTeng.de"/></From><To><User FriendlyName="Stein"/></To><Text Style="font-family:MS Shell Dlg; color:#000000; ">:)</Text></Message><Message Date="11/30/2007" Time="4:53:53 PM" DateTime="2007-11-30T15:53:53.531Z" SessionID="24"><From><User FriendlyName="Stein"/></From><To><User FriendlyName="紫龙  龙腾科技 德语王－商用网络电话　www.LongTeng.de"/></To><Text Style="font-family:Microsoft Sans Serif; font-weight:bold; color:#000000; ">你最近生意怎么样</Text></Message><Message Date="11/30/2007" Time="4:54:07 PM" DateTime="2007-11-30T15:54:07.703Z" SessionID="24"><From><User FriendlyName="紫龙  龙腾科技 德语王－商用网络电话　www.LongTeng.de"/></From><To><User FriendlyName="Stein"/></To><Text Style="font-family:MS Shell Dlg; color:#000000; ">电话</Text></Message><Message Date="11/30/2007" Time="4:54:13 PM" DateTime="2007-11-30T15:54:13.078Z" SessionID="24"><From><User FriendlyName="紫龙  龙腾科技 德语王－商用网络电话　www.LongTeng.de"/></From><To><User FriendlyName="Stein"/></To><Text Style="font-family:MS Shell Dlg; color:#000000; ">中</Text></Message><Message Date="11/30/2007" Time="4:54:26 PM" DateTime="2007-11-30T15:54:26.343Z" SessionID="24"><From><User FriendlyName="Stein"/></From><To><User FriendlyName="紫龙  龙腾科技 德语王－商用网络电话　www.LongTeng.de"/></To><Text Style="font-family:Microsoft Sans Serif; font-weight:bold; color:#000000; ">哦，你先忙</Text></Message><Message Date="7/16/2008" Time="9:49:24 PM" DateTime="2008-07-16T19:49:24.015Z" SessionID="25"><From><User FriendlyName="Stein"/></From><To><User FriendlyName="(R)紫龙 www.LongTeng.de"/></To><Text Style="font-family:Microsoft Sans Serif; font-weight:bold; color:#000000; ">hi</Text></Message><Message Date="7/16/2008" Time="9:49:43 PM" DateTime="2008-07-16T19:49:43.281Z" SessionID="25"><From><User FriendlyName="Stein"/></From><To><User FriendlyName="(R)紫龙 www.LongTeng.de"/></To><Text Style="font-family:Microsoft Sans Serif; font-weight:bold; color:#000000; ">最近好吗</Text></Message><Message Date="7/16/2008" Time="9:49:46 PM" DateTime="2008-07-16T19:49:46.687Z" SessionID="25"><From><User FriendlyName="(R)紫龙 www.LongTeng.de"/></From><To><User FriendlyName="Stein"/></To><Text Style="font-family:MS Shell Dlg; color:#000000; ">hi</Text></Message><Message Date="7/16/2008" Time="9:50:04 PM" DateTime="2008-07-16T19:50:04.703Z" SessionID="25"><From><User FriendlyName="(R)紫龙 www.LongTeng.de"/></From><To><User FriendlyName="Stein"/></To><Text Style="font-family:MS Shell Dlg; color:#000000; ">马马虎虎，老样子</Text></Message><Message Date="7/16/2008" Time="9:50:08 PM" DateTime="2008-07-16T19:50:08.625Z" SessionID="25"><From><User FriendlyName="Stein"/></From><To><User FriendlyName="(R)紫龙 www.LongTeng.de"/></To><Text Style="font-family:Microsoft Sans Serif; font-weight:bold; color:#000000; ">我的号码是不是已经取消了</Text></Message><Message Date="7/16/2008" Time="9:50:48 PM" DateTime="2008-07-16T19:50:48.109Z" SessionID="25"><From><User FriendlyName="(R)紫龙 www.LongTeng.de"/></From><To><User FriendlyName="Stein"/></To><Text Style="font-family:MS Shell Dlg; color:#000000; ">恩，因为欠费太久</Text></Message><Message Date="7/16/2008" Time="9:51:21 PM" DateTime="2008-07-16T19:51:21.593Z" SessionID="25"><From><User FriendlyName="Stein"/></From><To><User FriendlyName="(R)紫龙 www.LongTeng.de"/></To><Text Style="font-family:Microsoft Sans Serif; font-weight:bold; color:#000000; ">算了，付了费，我这o2也难用</Text></Message><Message Date="7/16/2008" Time="9:51:59 PM" DateTime="2008-07-16T19:51:59.765Z" SessionID="25"><From><User FriendlyName="(R)紫龙 www.LongTeng.de"/></From><To><User FriendlyName="Stein"/></To><Text Style="font-family:MS Shell Dlg; color:#000000; ">我可以帮你查查看，是否还可以恢复</Text></Message><Message Date="7/16/2008" Time="9:52:23 PM" DateTime="2008-07-16T19:52:23.000Z" SessionID="25"><From><User FriendlyName="Stein"/></From><To><User FriendlyName="(R)紫龙 www.LongTeng.de"/></To><Text Style="font-family:Microsoft Sans Serif; font-weight:bold; color:#000000; ">但02这东西。。</Text></Message><Message Date="7/16/2008" Time="9:52:30 PM" DateTime="2008-07-16T19:52:30.265Z" SessionID="25"><From><User FriendlyName="(R)紫龙 www.LongTeng.de"/></From><To><User FriendlyName="Stein"/></To><Text Style="font-family:MS Shell Dlg; color:#000000; ">也是</Text></Message><Message Date="7/16/2008" Time="9:52:46 PM" DateTime="2008-07-16T19:52:46.734Z" SessionID="25"><From><User FriendlyName="(R)紫龙 www.LongTeng.de"/></From><To><User FriendlyName="Stein"/></To><Text Style="font-family:MS Shell Dlg; color:#000000; ">最近忙什么？</Text></Message><Message Date="7/16/2008" Time="9:53:12 PM" DateTime="2008-07-16T19:53:12.781Z" SessionID="25"><From><User FriendlyName="Stein"/></From><To><User FriendlyName="(R)紫龙 www.LongTeng.de"/></To><Text Style="font-family:Microsoft Sans Serif; font-weight:bold; color:#000000; ">还有啥，上课，打工</Text></Message><Message Date="7/16/2008" Time="9:53:21 PM" DateTime="2008-07-16T19:53:21.312Z" SessionID="25"><From><User FriendlyName="Stein"/></From><To><User FriendlyName="(R)紫龙 www.LongTeng.de"/></To><Text Style="font-family:Microsoft Sans Serif; font-weight:bold; color:#000000; ">心情一直不是很好</Text></Message><Message Date="7/16/2008" Time="9:53:28 PM" DateTime="2008-07-16T19:53:28.921Z" SessionID="25"><From><User FriendlyName="Stein"/></From><To><User FriendlyName="(R)紫龙 www.LongTeng.de"/></To><Text Style="font-family:Microsoft Sans Serif; font-weight:bold; color:#000000; ">也没和你联系</Text></Message><Message Date="7/16/2008" Time="9:54:09 PM" DateTime="2008-07-16T19:54:09.031Z" SessionID="25"><From><User FriendlyName="(R)紫龙 www.LongTeng.de"/></From><To><User FriendlyName="Stein"/></To><Text Style="font-family:MS Shell Dlg; color:#000000; ">事情总会过去的</Text></Message><Message Date="7/16/2008" Time="9:54:22 PM" DateTime="2008-07-16T19:54:22.968Z" SessionID="25"><From><User FriendlyName="Stein"/></From><To><User FriendlyName="(R)紫龙 www.LongTeng.de"/></To><Text Style="font-family:Microsoft Sans Serif; font-weight:bold; color:#000000; ">恩</Text></Message><Message Date="7/16/2008" Time="9:54:47 PM" DateTime="2008-07-16T19:54:47.171Z" SessionID="25"><From><User FriendlyName="Stein"/></From><To><User FriendlyName="(R)紫龙 www.LongTeng.de"/></To><Text Style="font-family:Microsoft Sans Serif; font-weight:bold; color:#000000; ">你那有卖德语电子字典哦</Text></Message><Message Date="7/16/2008" Time="9:55:31 PM" DateTime="2008-07-16T19:55:31.687Z" SessionID="25"><From><User FriendlyName="(R)紫龙 www.LongTeng.de"/></From><To><User FriendlyName="Stein"/></To><Text Style="font-family:MS Shell Dlg; color:#000000; ">有</Text></Message><Message Date="7/16/2008" Time="9:56:12 PM" DateTime="2008-07-16T19:56:12.156Z" SessionID="25"><From><User FriendlyName="Stein"/></From><To><User FriendlyName="(R)紫龙 www.LongTeng.de"/></To><Text Style="font-family:Microsoft Sans Serif; font-weight:bold; color:#000000; ">感觉怎么样，质量</Text></Message><Message Date="7/16/2008" Time="9:56:31 PM" DateTime="2008-07-16T19:56:31.359Z" SessionID="25"><From><User FriendlyName="(R)紫龙 www.LongTeng.de"/></From><To><User FriendlyName="Stein"/></To><Text Style="font-family:MS Shell Dlg; color:#000000; ">还不错的，一直在做</Text></Message><Message Date="7/16/2008" Time="9:56:50 PM" DateTime="2008-07-16T19:56:50.515Z" SessionID="25"><From><User FriendlyName="Stein"/></From><To><User FriendlyName="(R)紫龙 www.LongTeng.de"/></To><Text Style="font-family:Microsoft Sans Serif; font-weight:bold; color:#000000; ">和那个国内的叫什么品牌我忘记了，哪个更好些</Text></Message><Message Date="7/16/2008" Time="9:57:44 PM" DateTime="2008-07-16T19:57:44.125Z" SessionID="25"><From><User FriendlyName="(R)紫龙 www.LongTeng.de"/></From><To><User FriendlyName="Stein"/></To><Text Style="font-family:MS Shell Dlg; color:#000000; ">快译点德语王</Text></Message><Message Date="7/16/2008" Time="9:58:35 PM" DateTime="2008-07-16T19:58:35.437Z" SessionID="25"><From><User FriendlyName="Stein"/></From><To><User FriendlyName="(R)紫龙 www.LongTeng.de"/></To><Text Style="font-family:Microsoft Sans Serif; font-weight:bold; color:#000000; ">我记得德国热线上卖68的那个</Text></Message><Message Date="7/16/2008" Time="10:01:12 PM" DateTime="2008-07-16T20:01:12.593Z" SessionID="25"><From><User FriendlyName="(R)紫龙 www.LongTeng.de"/></From><To><User FriendlyName="Stein"/></To><Text Style="font-family:MS Shell Dlg; color:#000000; ">我们这个卖95欧，不知道是不是你说的这个</Text></Message><Message Date="7/16/2008" Time="10:01:41 PM" DateTime="2008-07-16T20:01:41.406Z" SessionID="25"><From><User FriendlyName="Stein"/></From><To><User FriendlyName="(R)紫龙 www.LongTeng.de"/></To><Text Style="font-family:Microsoft Sans Serif; font-weight:bold; color:#000000; ">你的不是148吗</Text></Message><Message Date="7/16/2008" Time="10:01:54 PM" DateTime="2008-07-16T20:01:54.484Z" SessionID="25"><From><User FriendlyName="(R)紫龙 www.LongTeng.de"/></From><To><User FriendlyName="Stein"/></To><Text Style="font-family:MS Shell Dlg; color:#000000; ">学生价95</Text></Message><Message Date="7/16/2008" Time="10:02:24 PM" DateTime="2008-07-16T20:02:24.906Z" SessionID="25"><From><User FriendlyName="Stein"/></From><To><User FriendlyName="(R)紫龙 www.LongTeng.de"/></To><Text Style="font-family:Microsoft Sans Serif; font-weight:bold; color:#000000; ">你网上可没写</Text></Message><Message Date="7/16/2008" Time="10:02:44 PM" DateTime="2008-07-16T20:02:44.359Z" SessionID="25"><From><User FriendlyName="(R)紫龙 www.LongTeng.de"/></From><To><User FriendlyName="Stein"/></To><Text Style="font-family:MS Shell Dlg; color:#000000; ">写了</Text></Message><Message Date="7/16/2008" Time="10:03:25 PM" DateTime="2008-07-16T20:03:25.281Z" SessionID="25"><From><User FriendlyName="(R)紫龙 www.LongTeng.de"/></From><To><User FriendlyName="Stein"/></To><Text Style="font-family:MS Shell Dlg; color:#000000; ">http://www.longteng.de/zhcn/rhfk.htm</Text></Message><Message Date="7/16/2008" Time="10:03:36 PM" DateTime="2008-07-16T20:03:36.546Z" SessionID="25"><From><User FriendlyName="Stein"/></From><To><User FriendlyName="(R)紫龙 www.LongTeng.de"/></To><Text Style="font-family:Microsoft Sans Serif; font-weight:bold; color:#000000; ">你怎么也02的生意了</Text></Message><Message Date="7/16/2008" Time="10:05:49 PM" DateTime="2008-07-16T20:05:49.203Z" SessionID="25"><From><User FriendlyName="Stein"/></From><To><User FriendlyName="(R)紫龙 www.LongTeng.de"/></To><Text Style="font-family:Microsoft Sans Serif; font-weight:bold; color:#000000; ">好吧，要是我买再和你说</Text></Message><Message Date="7/16/2008" Time="10:06:08 PM" DateTime="2008-07-16T20:06:08.640Z" SessionID="25"><From><User FriendlyName="(R)紫龙 www.LongTeng.de"/></From><To><User FriendlyName="Stein"/></To><Text Style="font-family:MS Shell Dlg; color:#000000; ">ok,欢迎</Text></Message><Message Date="7/16/2008" Time="10:06:16 PM" DateTime="2008-07-16T20:06:16.015Z" SessionID="25"><From><User FriendlyName="Stein"/></From><To><User FriendlyName="(R)紫龙 www.LongTeng.de"/></To><Text Style="font-family:Microsoft Sans Serif; font-weight:bold; color:#000000; ">你在忙吧</Text></Message><Message Date="7/16/2008" Time="10:08:12 PM" DateTime="2008-07-16T20:08:12.812Z" SessionID="25"><From><User FriendlyName="(R)紫龙 www.LongTeng.de"/></From><To><User FriendlyName="Stein"/></To><Text Style="font-family:MS Shell Dlg; color:#000000; ">不客气</Text></Message><Message Date="7/16/2008" Time="10:08:39 PM" DateTime="2008-07-16T20:08:39.625Z" SessionID="26"><From><User FriendlyName="Stein"/></From><To><User FriendlyName="(R)紫龙 www.LongTeng.de"/></To><Text Style="font-family:Microsoft Sans Serif; font-weight:bold; color:#000000; ">你先忙，有机会再聊</Text></Message></Log>
