<?xml version="1.0"?>
<?xml-stylesheet type='text/xsl' href='MessageLog.xsl'?>
<Log FirstSessionID="1" LastSessionID="1"><Message Date="8/2/2007" Time="2:02:52 PM" DateTime="2007-08-02T12:02:52.687Z" SessionID="1"><From><User FriendlyName="牛气冲天"/></From><To><User FriendlyName="Yq.Wang"/><User FriendlyName="我TMD就是爱Fender(8)"/><User FriendlyName="KHL"/><User FriendlyName="紫龙  在德国使用深圳、上海座机号码！ 龙腾科技"/><User FriendlyName="海添"/></To><Text Style="font-family:楷体_GB2312; color:#800000; ">谁有JVC GR-D系列的DV


我的dv机子,买了几年了,最近发现那个原装的电池充不进电了,但是充电之时灯会闪烁....所以买了新的电池,但是发现新的电池充电时候充电指示灯不会闪烁.
所以来问一下,谁有这个系列的dv.\或者充电器...贡献我一下试试,我看看到底是什么地方有问题,谢谢啦
AKKU FÜR JVC GR D20 D20E D20E/X GR-D20E E E/X 
passend für:

GR D53EK GR-DZ7E GR D225E GR-D73EK GR-D220E 
GR-D230EK GR-PD1E GR D50E GR-D21E GR-DV500
GR D20 EX GR DV4000E GR DV3000 GR DVL108
GR DVL140 GR DVL155EG GR D93EK GR DV1800 
GR DVL160 EG GR DVL</Text></Message><Leave Date="8/2/2007" Time="2:02:58 PM" DateTime="2007-08-02T12:02:58.531Z" SessionID="1"><User FriendlyName="牛气冲天"/><Text Style="color:#800000; ">牛气冲天 已离开对话。</Text></Leave></Log>
